Workbook

Sheet README
A1: Audit analytics toolkit: Benford, duplicate payments, round sums and journal entry tests
A2: Sample / demonstration data only. No real company, vendor, employee or transaction.
A4: PURPOSE
A5: Run standard data analytics over a year of payments and journal entries, score each item, and produce a ranked list for targeted follow up. Anomalies were seeded into the sample data so detection can be tested against an answer key.
A7: SHEETS
A8: Parameters: thresholds, weights, authorised users (inputs, blue). Change a value and every flag recalculates.
A9: Vendors, Employees: master data used by the bank account match.
A10: Payments: one row per payment. Blue = input, black = formula. Flags and score are columns to the right.
A11: Benford: first digit test over all payments (counts, z statistics, MAD, chi square) with a chart.
A12: Vendor_Benford: the same test per vendor, plus the employee bank account match.
A13: COA, JE_Lines: chart of accounts and journal entry lines (inputs).
A14: JE_Entries: one row per journal entry number (number in brown from the engine, everything else formulas), with tests and score.
... A34: Blue font = input. Brown font = engine output pasted as values. Black = formula.

Sheet Parameters
A1: Parameters
A2: Sample / demonstration data only. No real company, vendor, employee or transaction.
A3: Inputs in blue. Weights drive the risk scores.
A4: Parameter | B4: Value | C4: Note
A5: Fiscal year start | B5: 45658 | C5: Population period
A6: Fiscal year end | B6: 46022 | C6: Population period
A7: Payment approval limit (USD) | B7: 5000 | C7: Payments at or above need the senior approver
A8: Senior approver code | B8: FIN_DIR | C8: Approver required at or above the limit
A9: Below limit band | B9: 0.05 | C9: Flag payments within this share below the limit
A10: Round sum modulus (USD) | B10: 1000 | C10: Amount is a multiple of this
A11: Round sum minimum (USD) | B11: 1000 | C11: Ignore smaller round amounts
A12: Near duplicate window (days) | B12: 30 | C12: Same vendor and amount within this many days
A13: Benford minimum payments per vendor | B13: 30 | C13: Vendor test is unreliable below this count
A14: Benford MAD threshold | B14: 0.015 | C14: First digit MAD above this is nonconformity (Nigrini)
A15: Benford z critical value | B15: 1.96 | C15: 5 percent two sided
A16: Chi square critical value (8 df, 5 percent) | B16: 15.507 | C16: Fixed statistical constant
A17: JE posting lag limit (days) | B17: 15 | C17: Posting date less document date
A18: Period end window (days) | B18: 3 | C18: Last days of the fiscal year
A19: JE approval limit (USD) | B19: 50000 | C19: Manual entries need extra approval at or above
A20: JE below limit band | B20: 0.05 | C20: Flag manual entries within this share below the limit
... A25: High risk cutoff, journal entries (score) | B25: 5 | C25: Score at or above is High
A27: Payment risk weights
A28: Duplicate payment (same vendor, invoice, amount) | B28: 5
A29: Near duplicate (same vendor and amount, different invoice) | B29: 3
A30: Round sum | B30: 2
A31: Just below approval limit | B31: 2
A32: Same day split above limit | B32: 3
A33: Approved below required authority | B33: 4
A34: Vendor bank account matches an employee | B34: 5
A35: Vendor fails Benford test | B35: 2
A37: Journal entry risk weights
A38: Unbalanced entry | B38: 5
A39: Posted on weekend | B39: 2
A40: Posted late versus document date | B40: 2
A41: Posted in last days of year | B41: 1
A42: Posted by user not authorised | B42: 3
A43: Manual entry to revenue | B43: 3
A44: Round total | B44: 2
A45: No description | B45: 2
A46: Manual entry just below approval limit | B46: 3
A47: Manual entry to suspense | B47: 2
A48: Number sequence gap before entry | B48: 1
A50: Authorised journal posting users
A51: FIN01
A52: FIN02
A53: FIN03
A54: FIN04
A55: FIN05
A56: SYS_AP
A57: SYS_AR
A58: SYS_PAY

Sheet Vendors
A1: Vendor master
A2: Sample / demonstration data only. No real company, vendor, employee or transaction.
A3: Synthetic. V038 bank account equals an employee bank account (seeded).
A4: Vendor ID | B4: Vendor name | C4: Bank account
A5: V001 | B5: Sample Supplier 001 | C5: ACC00104784
A6: V002 | B6: Sample Supplier 002 | C6: ACC00209513
A7: V003 | B7: Sample Supplier 003 | C7: ACC00314242
A8: V004 | B8: Sample Supplier 004 | C8: ACC00418971
A9: V005 | B9: Sample Supplier 005 | C9: ACC00523700
A10: V006 | B10: Sample Supplier 006 | C10: ACC00628429
A11: V007 | B11: Sample Supplier 007 | C11: ACC00733158
A12: V008 | B12: Sample Supplier 008 | C12: ACC00837887
A13: V009 | B13: Sample Supplier 009 | C13: ACC00942616
A14: V010 | B14: Sample Supplier 010 | C14: ACC01047345
A15: V011 | B15: Sample Supplier 011 | C15: ACC01152074
... A49: V045 | B49: Sample Supplier 045 | C49: ACC04712860

Sheet Employees
A1: Employee master
A2: Sample / demonstration data only. No real company, vendor, employee or transaction.
A3: Synthetic.
A4: Employee ID | B4: Bank account
A5: E001 | B5: ACC15485863
A6: E002 | B6: ACC30971726
A7: E003 | B7: ACC46457589
A8: E004 | B8: ACC61943452
A9: E005 | B9: ACC77429315
A10: E006 | B10: ACC92915178
A11: E007 | B11: ACC08401041
A12: E008 | B12: ACC23886904
A13: E009 | B13: ACC39372767
A14: E010 | B14: ACC54858630
A15: E011 | B15: ACC70344493
... A29: E025 | B29: ACC87146575

Sheet Payments
A1: Payments
A2: Sample / demonstration data only. No real company, vendor, employee or transaction.
A3: Columns A to F are inputs. Columns G onward are formulas.
A4: Payment ID | B4: Payment date | C4: Vendor | D4: Invoice no | E4: Amount (USD) | F4: Approver | G4: First digit | H4: Normalised invoice | I4: Duplicate | J4: Near duplicate | K4: Round sum | L4: Below limit | M4: Same day split | N4: Authority breach | O4: Employee bank match | P4: Vendor Benford flag | Q4: Risk score | R4: Priority
A5: P0001 | B5: 45658 | C5: V001 | D5: RENT2501 | E5: 85000 | F5: FIN_DIR | G5: =VALUE(LEFT(TEXT(E5,"0.00"),1)) -> 8 | H5: =UPPER(SUBSTITUTE(SUBSTITUTE(SUBSTITUTE(D5," ",""),"/",""),".","")) -> RENT2501 | I5: =IF(COUNTIFS($C$5:C5,C5,$H$5:H5,H5,$E$5:E5,E5)>1,1,0) -> 0 | J5: =IF(AND(I5=0,COUNTIFS($C$5:$C$634,C5,$E$5:$E$634,E5,$B$5:$B$634,">="&(B5-Parameters!$B$12),$B$5:$B$634,"<="&(B5+Parameters!$B$12),$H$5:$H$634,"<>"&H5)>0),1,0) -> 0 | K5: =IF(AND(E5>=Parameters!$B$11,ROUND(MOD(ROUND(E5,2),Parameters!$B$10),2)=0),1,0) -> 1 | L5: =IF(AND(E5<Parameters!$B$7,E5>=Parameters!$B$7*(1-Parameters!$B$9)),1,0) -> 0 | M5: =IF(AND(E5<Parameters!$B$7,COUNTIFS($C$5:$C$634,C5,$B$5:$B$634,B5)>1,SUMIFS($E$5:$E$634,$C$5:$C$634,C5,$B$5:$B$634,B5)>=Parameters!$B$7),1,0) -> 0 | N5: =IF(AND(E5>=Parameters!$B$7,F5<>Parameters!$B$8),1,0) -> 0 | O5: =INDEX(Vendor_Benford!$N$6:$N$50,MATCH(C5,Vendor_Benford!$A$6:$A$50,0)) -> 0 | P5: =INDEX(Vendor_Benford!$M$6:$M$50,MATCH(C5,Vendor_Benford!$A$6:$A$50,0)) -> 0 | Q5: =I5*Parameters!$B$28+J5*Parameters!$B$29+K5*Parameters!$B$30+L5*Parameters!$B$31+M5*Parameters!$B$32+N5*Parameters!$B$33+O5*Parameters!$B$34+P5*Parameters!$B$35 -> 2 | R5: =IF(Q5>=Parameters!$B$24,"High","")
A6: P0002 | B6: 45658 | C6: V010 | D6: INV10007 | E6: 45000 | F6: FIN_DIR | G6: =VALUE(LEFT(TEXT(E6,"0.00"),1)) -> 4 | H6: =UPPER(SUBSTITUTE(SUBSTITUTE(SUBSTITUTE(D6," ",""),"/",""),".","")) -> INV10007 | I6: =IF(COUNTIFS($C$5:C6,C6,$H$5:H6,H6,$E$5:E6,E6)>1,1,0) -> 0 | J6: =IF(AND(I6=0,COUNTIFS($C$5:$C$634,C6,$E$5:$E$634,E6,$B$5:$B$634,">="&(B6-Parameters!$B$12),$B$5:$B$634,"<="&(B6+Parameters!$B$12),$H$5:$H$634,"<>"&H6)>0),1,0) -> 0 | K6: =IF(AND(E6>=Parameters!$B$11,ROUND(MOD(ROUND(E6,2),Parameters!$B$10),2)=0),1,0) -> 1 | L6: =IF(AND(E6<Parameters!$B$7,E6>=Parameters!$B$7*(1-Parameters!$B$9)),1,0) -> 0 | M6: =IF(AND(E6<Parameters!$B$7,COUNTIFS($C$5:$C$634,C6,$B$5:$B$634,B6)>1,SUMIFS($E$5:$E$634,$C$5:$C$634,C6,$B$5:$B$634,B6)>=Parameters!$B$7),1,0) -> 0 | N6: =IF(AND(E6>=Parameters!$B$7,F6<>Parameters!$B$8),1,0) -> 0 | O6: =INDEX(Vendor_Benford!$N$6:$N$50,MATCH(C6,Vendor_Benford!$A$6:$A$50,0)) -> 0 | P6: =INDEX(Vendor_Benford!$M$6:$M$50,MATCH(C6,Vendor_Benford!$A$6:$A$50,0)) -> 0 | Q6: =I6*Parameters!$B$28+J6*Parameters!$B$29+K6*Parameters!$B$30+L6*Parameters!$B$31+M6*Parameters!$B$32+N6*Parameters!$B$33+O6*Parameters!$B$34+P6*Parameters!$B$35 -> 2 | R6: =IF(Q6>=Parameters!$B$24,"High","")
A7: P0003 | B7: 45658 | C7: V030 | D7: INV30011 | E7: 684.73 | F7: FIN_DIR | G7: =VALUE(LEFT(TEXT(E7,"0.00"),1)) -> 6 | H7: =UPPER(SUBSTITUTE(SUBSTITUTE(SUBSTITUTE(D7," ",""),"/",""),".","")) -> INV30011 | I7: =IF(COUNTIFS($C$5:C7,C7,$H$5:H7,H7,$E$5:E7,E7)>1,1,0) -> 0 | J7: =IF(AND(I7=0,COUNTIFS($C$5:$C$634,C7,$E$5:$E$634,E7,$B$5:$B$634,">="&(B7-Parameters!$B$12),$B$5:$B$634,"<="&(B7+Parameters!$B$12),$H$5:$H$634,"<>"&H7)>0),1,0) -> 0 | K7: =IF(AND(E7>=Parameters!$B$11,ROUND(MOD(ROUND(E7,2),Parameters!$B$10),2)=0),1,0) -> 0 | L7: =IF(AND(E7<Parameters!$B$7,E7>=Parameters!$B$7*(1-Parameters!$B$9)),1,0) -> 0 | M7: =IF(AND(E7<Parameters!$B$7,COUNTIFS($C$5:$C$634,C7,$B$5:$B$634,B7)>1,SUMIFS($E$5:$E$634,$C$5:$C$634,C7,$B$5:$B$634,B7)>=Parameters!$B$7),1,0) -> 0 | N7: =IF(AND(E7>=Parameters!$B$7,F7<>Parameters!$B$8),1,0) -> 0 | O7: =INDEX(Vendor_Benford!$N$6:$N$50,MATCH(C7,Vendor_Benford!$A$6:$A$50,0)) -> 0 | P7: =INDEX(Vendor_Benford!$M$6:$M$50,MATCH(C7,Vendor_Benford!$A$6:$A$50,0)) -> 0 | Q7: =I7*Parameters!$B$28+J7*Parameters!$B$29+K7*Parameters!$B$30+L7*Parameters!$B$31+M7*Parameters!$B$32+N7*Parameters!$B$33+O7*Parameters!$B$34+P7*Parameters!$B$35 -> 0 | R7: =IF(Q7>=Parameters!$B$24,"High","")
A8: P0004 | B8: 45658 | C8: V039 | D8: INV39011 | E8: 14935.84 | F8: FIN_DIR | G8: =VALUE(LEFT(TEXT(E8,"0.00"),1)) -> 1 | H8: =UPPER(SUBSTITUTE(SUBSTITUTE(SUBSTITUTE(D8," ",""),"/",""),".","")) -> INV39011 | I8: =IF(COUNTIFS($C$5:C8,C8,$H$5:H8,H8,$E$5:E8,E8)>1,1,0) -> 0 | J8: =IF(AND(I8=0,COUNTIFS($C$5:$C$634,C8,$E$5:$E$634,E8,$B$5:$B$634,">="&(B8-Parameters!$B$12),$B$5:$B$634,"<="&(B8+Parameters!$B$12),$H$5:$H$634,"<>"&H8)>0),1,0) -> 0 | K8: =IF(AND(E8>=Parameters!$B$11,ROUND(MOD(ROUND(E8,2),Parameters!$B$10),2)=0),1,0) -> 0 | L8: =IF(AND(E8<Parameters!$B$7,E8>=Parameters!$B$7*(1-Parameters!$B$9)),1,0) -> 0 | M8: =IF(AND(E8<Parameters!$B$7,COUNTIFS($C$5:$C$634,C8,$B$5:$B$634,B8)>1,SUMIFS($E$5:$E$634,$C$5:$C$634,C8,$B$5:$B$634,B8)>=Parameters!$B$7),1,0) -> 0 | N8: =IF(AND(E8>=Parameters!$B$7,F8<>Parameters!$B$8),1,0) -> 0 | O8: =INDEX(Vendor_Benford!$N$6:$N$50,MATCH(C8,Vendor_Benford!$A$6:$A$50,0)) -> 0 | P8: =INDEX(Vendor_Benford!$M$6:$M$50,MATCH(C8,Vendor_Benford!$A$6:$A$50,0)) -> 0 | Q8: =I8*Parameters!$B$28+J8*Parameters!$B$29+K8*Parameters!$B$30+L8*Parameters!$B$31+M8*Parameters!$B$32+N8*Parameters!$B$33+O8*Parameters!$B$34+P8*Parameters!$B$35 -> 0 | R8: =IF(Q8>=Parameters!$B$24,"High","")
A9: P0005 | B9: 45658 | C9: V042 | D9: INV42010 | E9: 5020.85 | F9: FIN_DIR | G9: =VALUE(LEFT(TEXT(E9,"0.00"),1)) -> 5 | H9: =UPPER(SUBSTITUTE(SUBSTITUTE(SUBSTITUTE(D9," ",""),"/",""),".","")) -> INV42010 | I9: =IF(COUNTIFS($C$5:C9,C9,$H$5:H9,H9,$E$5:E9,E9)>1,1,0) -> 0 | J9: =IF(AND(I9=0,COUNTIFS($C$5:$C$634,C9,$E$5:$E$634,E9,$B$5:$B$634,">="&(B9-Parameters!$B$12),$B$5:$B$634,"<="&(B9+Parameters!$B$12),$H$5:$H$634,"<>"&H9)>0),1,0) -> 0 | K9: =IF(AND(E9>=Parameters!$B$11,ROUND(MOD(ROUND(E9,2),Parameters!$B$10),2)=0),1,0) -> 0 | L9: =IF(AND(E9<Parameters!$B$7,E9>=Parameters!$B$7*(1-Parameters!$B$9)),1,0) -> 0 | M9: =IF(AND(E9<Parameters!$B$7,COUNTIFS($C$5:$C$634,C9,$B$5:$B$634,B9)>1,SUMIFS($E$5:$E$634,$C$5:$C$634,C9,$B$5:$B$634,B9)>=Parameters!$B$7),1,0) -> 0 | N9: =IF(AND(E9>=Parameters!$B$7,F9<>Parameters!$B$8),1,0) -> 0 | O9: =INDEX(Vendor_Benford!$N$6:$N$50,MATCH(C9,Vendor_Benford!$A$6:$A$50,0)) -> 0 | P9: =INDEX(Vendor_Benford!$M$6:$M$50,MATCH(C9,Vendor_Benford!$A$6:$A$50,0)) -> 0 | Q9: =I9*Parameters!$B$28+J9*Parameters!$B$29+K9*Parameters!$B$30+L9*Parameters!$B$31+M9*Parameters!$B$32+N9*Parameters!$B$33+O9*Parameters!$B$34+P9*Parameters!$B$35 -> 0 | R9: =IF(Q9>=Parameters!$B$24,"High","")
A10: P0006 | B10: 45659 | C10: V044 | D10: INV44006 | E10: 20651.24 | F10: FIN_DIR | G10: =VALUE(LEFT(TEXT(E10,"0.00"),1)) -> 2 | H10: =UPPER(SUBSTITUTE(SUBSTITUTE(SUBSTITUTE(D10," ",""),"/",""),".","")) -> INV44006 | I10: =IF(COUNTIFS($C$5:C10,C10,$H$5:H10,H10,$E$5:E10,E10)>1,1,0) -> 0 | J10: =IF(AND(I10=0,COUNTIFS($C$5:$C$634,C10,$E$5:$E$634,E10,$B$5:$B$634,">="&(B10-Parameters!$B$12),$B$5:$B$634,"<="&(B10+Parameters!$B$12),$H$5:$H$634,"<>"&H10)>0),1,0) -> 0 | K10: =IF(AND(E10>=Parameters!$B$11,ROUND(MOD(ROUND(E10,2),Parameters!$B$10),2)=0),1,0) -> 0 | L10: =IF(AND(E10<Parameters!$B$7,E10>=Parameters!$B$7*(1-Parameters!$B$9)),1,0) -> 0 | M10: =IF(AND(E10<Parameters!$B$7,COUNTIFS($C$5:$C$634,C10,$B$5:$B$634,B10)>1,SUMIFS($E$5:$E$634,$C$5:$C$634,C10,$B$5:$B$634,B10)>=Parameters!$B$7),1,0) -> 0 | N10: =IF(AND(E10>=Parameters!$B$7,F10<>Parameters!$B$8),1,0) -> 0 | O10: =INDEX(Vendor_Benford!$N$6:$N$50,MATCH(C10,Vendor_Benford!$A$6:$A$50,0)) -> 0 | P10: =INDEX(Vendor_Benford!$M$6:$M$50,MATCH(C10,Vendor_Benford!$A$6:$A$50,0)) -> 0 | Q10: =I10*Parameters!$B$28+J10*Parameters!$B$29+K10*Parameters!$B$30+L10*Parameters!$B$31+M10*Parameters!$B$32+N10*Parameters!$B$33+O10*Parameters!$B$34+P10*Parameters!$B$35 -> 0 | R10: =IF(Q10>=Parameters!$B$24,"High","")
A11: P0007 | B11: 45659 | C11: V045 | D11: INV45004 | E11: 9042.65 | F11: FIN_DIR | G11: =VALUE(LEFT(TEXT(E11,"0.00"),1)) -> 9 | H11: =UPPER(SUBSTITUTE(SUBSTITUTE(SUBSTITUTE(D11," ",""),"/",""),".","")) -> INV45004 | I11: =IF(COUNTIFS($C$5:C11,C11,$H$5:H11,H11,$E$5:E11,E11)>1,1,0) -> 0 | J11: =IF(AND(I11=0,COUNTIFS($C$5:$C$634,C11,$E$5:$E$634,E11,$B$5:$B$634,">="&(B11-Parameters!$B$12),$B$5:$B$634,"<="&(B11+Parameters!$B$12),$H$5:$H$634,"<>"&H11)>0),1,0) -> 0 | K11: =IF(AND(E11>=Parameters!$B$11,ROUND(MOD(ROUND(E11,2),Parameters!$B$10),2)=0),1,0) -> 0 | L11: =IF(AND(E11<Parameters!$B$7,E11>=Parameters!$B$7*(1-Parameters!$B$9)),1,0) -> 0 | M11: =IF(AND(E11<Parameters!$B$7,COUNTIFS($C$5:$C$634,C11,$B$5:$B$634,B11)>1,SUMIFS($E$5:$E$634,$C$5:$C$634,C11,$B$5:$B$634,B11)>=Parameters!$B$7),1,0) -> 0 | N11: =IF(AND(E11>=Parameters!$B$7,F11<>Parameters!$B$8),1,0) -> 0 | O11: =INDEX(Vendor_Benford!$N$6:$N$50,MATCH(C11,Vendor_Benford!$A$6:$A$50,0)) -> 0 | P11: =INDEX(Vendor_Benford!$M$6:$M$50,MATCH(C11,Vendor_Benford!$A$6:$A$50,0)) -> 0 | Q11: =I11*Parameters!$B$28+J11*Parameters!$B$29+K11*Parameters!$B$30+L11*Parameters!$B$31+M11*Parameters!$B$32+N11*Parameters!$B$33+O11*Parameters!$B$34+P11*Parameters!$B$35 -> 0 | R11: =IF(Q11>=Parameters!$B$24,"High","")
A12: P0008 | B12: 45660 | C12: V012 | D12: INV12012 | E12: 6340.75 | F12: FIN_DIR | G12: =VALUE(LEFT(TEXT(E12,"0.00"),1)) -> 6 | H12: =UPPER(SUBSTITUTE(SUBSTITUTE(SUBSTITUTE(D12," ",""),"/",""),".","")) -> INV12012 | I12: =IF(COUNTIFS($C$5:C12,C12,$H$5:H12,H12,$E$5:E12,E12)>1,1,0) -> 0 | J12: =IF(AND(I12=0,COUNTIFS($C$5:$C$634,C12,$E$5:$E$634,E12,$B$5:$B$634,">="&(B12-Parameters!$B$12),$B$5:$B$634,"<="&(B12+Parameters!$B$12),$H$5:$H$634,"<>"&H12)>0),1,0) -> 0 | K12: =IF(AND(E12>=Parameters!$B$11,ROUND(MOD(ROUND(E12,2),Parameters!$B$10),2)=0),1,0) -> 0 | L12: =IF(AND(E12<Parameters!$B$7,E12>=Parameters!$B$7*(1-Parameters!$B$9)),1,0) -> 0 | M12: =IF(AND(E12<Parameters!$B$7,COUNTIFS($C$5:$C$634,C12,$B$5:$B$634,B12)>1,SUMIFS($E$5:$E$634,$C$5:$C$634,C12,$B$5:$B$634,B12)>=Parameters!$B$7),1,0) -> 0 | N12: =IF(AND(E12>=Parameters!$B$7,F12<>Parameters!$B$8),1,0) -> 0 | O12: =INDEX(Vendor_Benford!$N$6:$N$50,MATCH(C12,Vendor_Benford!$A$6:$A$50,0)) -> 0 | P12: =INDEX(Vendor_Benford!$M$6:$M$50,MATCH(C12,Vendor_Benford!$A$6:$A$50,0)) -> 0 | Q12: =I12*Parameters!$B$28+J12*Parameters!$B$29+K12*Parameters!$B$30+L12*Parameters!$B$31+M12*Parameters!$B$32+N12*Parameters!$B$33+O12*Parameters!$B$34+P12*Parameters!$B$35 -> 0 | R12: =IF(Q12>=Parameters!$B$24,"High","")
A13: P0009 | B13: 45660 | C13: V022 | D13: INV22005 | E13: 14791.69 | F13: FIN_DIR | G13: =VALUE(LEFT(TEXT(E13,"0.00"),1)) -> 1 | H13: =UPPER(SUBSTITUTE(SUBSTITUTE(SUBSTITUTE(D13," ",""),"/",""),".","")) -> INV22005 | I13: =IF(COUNTIFS($C$5:C13,C13,$H$5:H13,H13,$E$5:E13,E13)>1,1,0) -> 0 | J13: =IF(AND(I13=0,COUNTIFS($C$5:$C$634,C13,$E$5:$E$634,E13,$B$5:$B$634,">="&(B13-Parameters!$B$12),$B$5:$B$634,"<="&(B13+Parameters!$B$12),$H$5:$H$634,"<>"&H13)>0),1,0) -> 0 | K13: =IF(AND(E13>=Parameters!$B$11,ROUND(MOD(ROUND(E13,2),Parameters!$B$10),2)=0),1,0) -> 0 | L13: =IF(AND(E13<Parameters!$B$7,E13>=Parameters!$B$7*(1-Parameters!$B$9)),1,0) -> 0 | M13: =IF(AND(E13<Parameters!$B$7,COUNTIFS($C$5:$C$634,C13,$B$5:$B$634,B13)>1,SUMIFS($E$5:$E$634,$C$5:$C$634,C13,$B$5:$B$634,B13)>=Parameters!$B$7),1,0) -> 0 | N13: =IF(AND(E13>=Parameters!$B$7,F13<>Parameters!$B$8),1,0) -> 0 | O13: =INDEX(Vendor_Benford!$N$6:$N$50,MATCH(C13,Vendor_Benford!$A$6:$A$50,0)) -> 0 | P13: =INDEX(Vendor_Benford!$M$6:$M$50,MATCH(C13,Vendor_Benford!$A$6:$A$50,0)) -> 0 | Q13: =I13*Parameters!$B$28+J13*Parameters!$B$29+K13*Parameters!$B$30+L13*Parameters!$B$31+M13*Parameters!$B$32+N13*Parameters!$B$33+O13*Parameters!$B$34+P13*Parameters!$B$35 -> 0 | R13: =IF(Q13>=Parameters!$B$24,"High","")
A14: P0010 | B14: 45663 | C14: V003 | D14: INV3013 | E14: 65754.59 | F14: FIN_DIR | G14: =VALUE(LEFT(TEXT(E14,"0.00"),1)) -> 6 | H14: =UPPER(SUBSTITUTE(SUBSTITUTE(SUBSTITUTE(D14," ",""),"/",""),".","")) -> INV3013 | I14: =IF(COUNTIFS($C$5:C14,C14,$H$5:H14,H14,$E$5:E14,E14)>1,1,0) -> 0 | J14: =IF(AND(I14=0,COUNTIFS($C$5:$C$634,C14,$E$5:$E$634,E14,$B$5:$B$634,">="&(B14-Parameters!$B$12),$B$5:$B$634,"<="&(B14+Parameters!$B$12),$H$5:$H$634,"<>"&H14)>0),1,0) -> 0 | K14: =IF(AND(E14>=Parameters!$B$11,ROUND(MOD(ROUND(E14,2),Parameters!$B$10),2)=0),1,0) -> 0 | L14: =IF(AND(E14<Parameters!$B$7,E14>=Parameters!$B$7*(1-Parameters!$B$9)),1,0) -> 0 | M14: =IF(AND(E14<Parameters!$B$7,COUNTIFS($C$5:$C$634,C14,$B$5:$B$634,B14)>1,SUMIFS($E$5:$E$634,$C$5:$C$634,C14,$B$5:$B$634,B14)>=Parameters!$B$7),1,0) -> 0 | N14: =IF(AND(E14>=Parameters!$B$7,F14<>Parameters!$B$8),1,0) -> 0 | O14: =INDEX(Vendor_Benford!$N$6:$N$50,MATCH(C14,Vendor_Benford!$A$6:$A$50,0)) -> 0 | P14: =INDEX(Vendor_Benford!$M$6:$M$50,MATCH(C14,Vendor_Benford!$A$6:$A$50,0)) -> 0 | Q14: =I14*Parameters!$B$28+J14*Parameters!$B$29+K14*Parameters!$B$30+L14*Parameters!$B$31+M14*Parameters!$B$32+N14*Parameters!$B$33+O14*Parameters!$B$34+P14*Parameters!$B$35 -> 0 | R14: =IF(Q14>=Parameters!$B$24,"High","")
A15: P0011 | B15: 45663 | C15: V020 | D15: INV20012 | E15: 2622.95 | F15: FIN_DIR | G15: =VALUE(LEFT(TEXT(E15,"0.00"),1)) -> 2 | H15: =UPPER(SUBSTITUTE(SUBSTITUTE(SUBSTITUTE(D15," ",""),"/",""),".","")) -> INV20012 | I15: =IF(COUNTIFS($C$5:C15,C15,$H$5:H15,H15,$E$5:E15,E15)>1,1,0) -> 0 | J15: =IF(AND(I15=0,COUNTIFS($C$5:$C$634,C15,$E$5:$E$634,E15,$B$5:$B$634,">="&(B15-Parameters!$B$12),$B$5:$B$634,"<="&(B15+Parameters!$B$12),$H$5:$H$634,"<>"&H15)>0),1,0) -> 0 | K15: =IF(AND(E15>=Parameters!$B$11,ROUND(MOD(ROUND(E15,2),Parameters!$B$10),2)=0),1,0) -> 0 | L15: =IF(AND(E15<Parameters!$B$7,E15>=Parameters!$B$7*(1-Parameters!$B$9)),1,0) -> 0 | M15: =IF(AND(E15<Parameters!$B$7,COUNTIFS($C$5:$C$634,C15,$B$5:$B$634,B15)>1,SUMIFS($E$5:$E$634,$C$5:$C$634,C15,$B$5:$B$634,B15)>=Parameters!$B$7),1,0) -> 0 | N15: =IF(AND(E15>=Parameters!$B$7,F15<>Parameters!$B$8),1,0) -> 0 | O15: =INDEX(Vendor_Benford!$N$6:$N$50,MATCH(C15,Vendor_Benford!$A$6:$A$50,0)) -> 0 | P15: =INDEX(Vendor_Benford!$M$6:$M$50,MATCH(C15,Vendor_Benford!$A$6:$A$50,0)) -> 0 | Q15: =I15*Parameters!$B$28+J15*Parameters!$B$29+K15*Parameters!$B$30+L15*Parameters!$B$31+M15*Parameters!$B$32+N15*Parameters!$B$33+O15*Parameters!$B$34+P15*Parameters!$B$35 -> 0 | R15: =IF(Q15>=Parameters!$B$24,"High","")
A16: P0012 | B16: 45664 | C16: V012 | D16: INV12012 | E16: 6340.75 | F16: FIN_DIR | G16: =VALUE(LEFT(TEXT(E16,"0.00"),1)) -> 6 | H16: =UPPER(SUBSTITUTE(SUBSTITUTE(SUBSTITUTE(D16," ",""),"/",""),".","")) -> INV12012 | I16: =IF(COUNTIFS($C$5:C16,C16,$H$5:H16,H16,$E$5:E16,E16)>1,1,0) -> 1 | J16: =IF(AND(I16=0,COUNTIFS($C$5:$C$634,C16,$E$5:$E$634,E16,$B$5:$B$634,">="&(B16-Parameters!$B$12),$B$5:$B$634,"<="&(B16+Parameters!$B$12),$H$5:$H$634,"<>"&H16)>0),1,0) -> 0 | K16: =IF(AND(E16>=Parameters!$B$11,ROUND(MOD(ROUND(E16,2),Parameters!$B$10),2)=0),1,0) -> 0 | L16: =IF(AND(E16<Parameters!$B$7,E16>=Parameters!$B$7*(1-Parameters!$B$9)),1,0) -> 0 | M16: =IF(AND(E16<Parameters!$B$7,COUNTIFS($C$5:$C$634,C16,$B$5:$B$634,B16)>1,SUMIFS($E$5:$E$634,$C$5:$C$634,C16,$B$5:$B$634,B16)>=Parameters!$B$7),1,0) -> 0 | N16: =IF(AND(E16>=Parameters!$B$7,F16<>Parameters!$B$8),1,0) -> 0 | O16: =INDEX(Vendor_Benford!$N$6:$N$50,MATCH(C16,Vendor_Benford!$A$6:$A$50,0)) -> 0 | P16: =INDEX(Vendor_Benford!$M$6:$M$50,MATCH(C16,Vendor_Benford!$A$6:$A$50,0)) -> 0 | Q16: =I16*Parameters!$B$28+J16*Parameters!$B$29+K16*Parameters!$B$30+L16*Parameters!$B$31+M16*Parameters!$B$32+N16*Parameters!$B$33+O16*Parameters!$B$34+P16*Parameters!$B$35 -> 5 | R16: =IF(Q16>=Parameters!$B$24,"High","") -> High
... A634: P0630 | B634: 46022 | C634: V033 | D634: INV33005 | E634: 3185.98 | F634: FIN_DIR | G634: =VALUE(LEFT(TEXT(E634,"0.00"),1)) -> 3 | H634: =UPPER(SUBSTITUTE(SUBSTITUTE(SUBSTITUTE(D634," ",""),"/",""),".","")) -> INV33005 | I634: =IF(COUNTIFS($C$5:C634,C634,$H$5:H634,H634,$E$5:E634,E634)>1,1,0) -> 0 | J634: =IF(AND(I634=0,COUNTIFS($C$5:$C$634,C634,$E$5:$E$634,E634,$B$5:$B$634,">="&(B634-Parameters!$B$12),$B$5:$B$634,"<="&(B634+Parameters!$B$12),$H$5:$H$634,"<>"&H634)>0),1,0) -> 0 | K634: =IF(AND(E634>=Parameters!$B$11,ROUND(MOD(ROUND(E634,2),Parameters!$B$10),2)=0),1,0) -> 0 | L634: =IF(AND(E634<Parameters!$B$7,E634>=Parameters!$B$7*(1-Parameters!$B$9)),1,0) -> 0 | M634: =IF(AND(E634<Parameters!$B$7,COUNTIFS($C$5:$C$634,C634,$B$5:$B$634,B634)>1,SUMIFS($E$5:$E$634,$C$5:$C$634,C634,$B$5:$B$634,B634)>=Parameters!$B$7),1,0) -> 0 | N634: =IF(AND(E634>=Parameters!$B$7,F634<>Parameters!$B$8),1,0) -> 0 | O634: =INDEX(Vendor_Benford!$N$6:$N$50,MATCH(C634,Vendor_Benford!$A$6:$A$50,0)) -> 0 | P634: =INDEX(Vendor_Benford!$M$6:$M$50,MATCH(C634,Vendor_Benford!$A$6:$A$50,0)) -> 0 | Q634: =I634*Parameters!$B$28+J634*Parameters!$B$29+K634*Parameters!$B$30+L634*Parameters!$B$31+M634*Parameters!$B$32+N634*Parameters!$B$33+O634*Parameters!$B$34+P634*Parameters!$B$35 -> 0 | R634: =IF(Q634>=Parameters!$B$24,"High","")

Sheet Benford
A1: Benford's Law, first digit test, all payments
A2: Sample / demonstration data only. No real company, vendor, employee or transaction.
A3: z uses the continuity correction. MAD is the mean absolute deviation across nine digits.
A4: First digit | B4: Count | C4: Actual % | D4: Expected % | E4: Difference | F4: z statistic | G4: Significant at 5 percent? | H4: Chi square term
A5: 1 | B5: =COUNTIF(Payments!$G$5:$G$634,A5) -> 169 | C5: =B5/$B$15 -> 0.26825397 | D5: =LOG10(1+1/A5) -> 0.30103 | E5: =C5-D5 -> -0.032776027 | F5: =MAX(0,ABS(E5)-1/(2*$B$15))/SQRT(D5*(1-D5)/$B$15) -> 1.7500355 | G5: =IF(F5>Parameters!$B$15,"Yes","No") -> No | H5: =$B$15*(C5-D5)^2/D5 -> 2.2482438
A6: 2 | B6: =COUNTIF(Payments!$G$5:$G$634,A6) -> 116 | C6: =B6/$B$15 -> 0.18412698 | D6: =LOG10(1+1/A6) -> 0.17609126 | E6: =C6-D6 -> 0.0080357251 | F6: =MAX(0,ABS(E6)-1/(2*$B$15))/SQRT(D6*(1-D6)/$B$15) -> 0.47722677 | G6: =IF(F6>Parameters!$B$15,"Yes","No") -> No | H6: =$B$15*(C6-D6)^2/D6 -> 0.23102176
A7: 3 | B7: =COUNTIF(Payments!$G$5:$G$634,A7) -> 56 | C7: =B7/$B$15 -> 0.088888889 | D7: =LOG10(1+1/A7) -> 0.12493874 | E7: =C7-D7 -> -0.036049848 | F7: =MAX(0,ABS(E7)-1/(2*$B$15))/SQRT(D7*(1-D7)/$B$15) -> 2.6763195 | G7: =IF(F7>Parameters!$B$15,"Yes","No") -> Yes | H7: =$B$15*(C7-D7)^2/D7 -> 6.553153
A8: 4 | B8: =COUNTIF(Payments!$G$5:$G$634,A8) -> 111 | C8: =B8/$B$15 -> 0.17619048 | D8: =LOG10(1+1/A8) -> 0.096910013 | E8: =C8-D8 -> 0.079280463 | F8: =MAX(0,ABS(E8)-1/(2*$B$15))/SQRT(D8*(1-D8)/$B$15) -> 6.6591244 | G8: =IF(F8>Parameters!$B$15,"Yes","No") -> Yes | H8: =$B$15*(C8-D8)^2/D8 -> 40.860554
A9: 5 | B9: =COUNTIF(Payments!$G$5:$G$634,A9) -> 44 | C9: =B9/$B$15 -> 0.06984127 | D9: =LOG10(1+1/A9) -> 0.079181246 | E9: =C9-D9 -> -0.0093399762 | F9: =MAX(0,ABS(E9)-1/(2*$B$15))/SQRT(D9*(1-D9)/$B$15) -> 0.79442235 | G9: =IF(F9>Parameters!$B$15,"Yes","No") -> No | H9: =$B$15*(C9-D9)^2/D9 -> 0.69408036
A10: 6 | B10: =COUNTIF(Payments!$G$5:$G$634,A10) -> 41 | C10: =B10/$B$15 -> 0.065079365 | D10: =LOG10(1+1/A10) -> 0.06694679 | E10: =C10-D10 -> -0.0018674246 | F10: =MAX(0,ABS(E10)-1/(2*$B$15))/SQRT(D10*(1-D10)/$B$15) -> 0.1078363 | G10: =IF(F10>Parameters!$B$15,"Yes","No") -> No | H10: =$B$15*(C10-D10)^2/D10 -> 0.032816852
A11: 7 | B11: =COUNTIF(Payments!$G$5:$G$634,A11) -> 31 | C11: =B11/$B$15 -> 0.049206349 | D11: =LOG10(1+1/A11) -> 0.057991947 | E11: =C11-D11 -> -0.0087855978 | F11: =MAX(0,ABS(E11)-1/(2*$B$15))/SQRT(D11*(1-D11)/$B$15) -> 0.85824586 | G11: =IF(F11>Parameters!$B$15,"Yes","No") -> No | H11: =$B$15*(C11-D11)^2/D11 -> 0.83852399
A12: 8 | B12: =COUNTIF(Payments!$G$5:$G$634,A12) -> 39 | C12: =B12/$B$15 -> 0.061904762 | D12: =LOG10(1+1/A12) -> 0.051152522 | E12: =C12-D12 -> 0.010752239 | F12: =MAX(0,ABS(E12)-1/(2*$B$15))/SQRT(D12*(1-D12)/$B$15) -> 1.1345832 | G12: =IF(F12>Parameters!$B$15,"Yes","No") -> No | H12: =$B$15*(C12-D12)^2/D12 -> 1.4238733
A13: 9 | B13: =COUNTIF(Payments!$G$5:$G$634,A13) -> 23 | C13: =B13/$B$15 -> 0.036507937 | D13: =LOG10(1+1/A13) -> 0.045757491 | E13: =C13-D13 -> -0.0092495541 | F13: =MAX(0,ABS(E13)-1/(2*$B$15))/SQRT(D13*(1-D13)/$B$15) -> 1.0157102 | G13: =IF(F13>Parameters!$B$15,"Yes","No") -> No | H13: =$B$15*(C13-D13)^2/D13 -> 1.1779312
A15: Total payments (n) | B15: =SUM(B5:B13) -> 630
A16: MAD | B16: =SUMPRODUCT(ABS(E5:E13))/9 -> 0.021792984
A17: Conformity (MAD bands) | B17: =IF(B16<=0.006,"Close conformity",IF(B16<=0.012,"Acceptable conformity",IF(B16<=0.015,"Marginally acceptable conformity","Nonconformity"))) -> Nonconformity
A18: Chi square | B18: =SUM(H5:H13) -> 54.060199
A19: Chi square critical (8 df, 5 percent) | B19: =Parameters!$B$16 -> 15.507
A20: Chi square result | B20: =IF(B18>B19,"Reject conformity","Do not reject") -> Reject conformity
A21: Digits significant at 5 percent | B21: =COUNTIF(G5:G13,"Yes") -> 2

Sheet Vendor_Benford
A1: Vendor level Benford test and employee bank match
A2: Sample / demonstration data only. No real company, vendor, employee or transaction.
A3: Expected proportions in row 5. Flag needs the minimum payment count on the Parameters sheet.
A4: Vendor | B4: Payments (n) | C4: Digit 1 | D4: Digit 2 | E4: Digit 3 | F4: Digit 4 | G4: Digit 5 | H4: Digit 6 | I4: Digit 7 | J4: Digit 8 | K4: Digit 9 | L4: MAD | M4: Benford flag | N4: Employee bank match
A5: Expected | C5: =LOG10(1+1/1) -> 0.30103 | D5: =LOG10(1+1/2) -> 0.17609126 | E5: =LOG10(1+1/3) -> 0.12493874 | F5: =LOG10(1+1/4) -> 0.096910013 | G5: =LOG10(1+1/5) -> 0.079181246 | H5: =LOG10(1+1/6) -> 0.06694679 | I5: =LOG10(1+1/7) -> 0.057991947 | J5: =LOG10(1+1/8) -> 0.051152522 | K5: =LOG10(1+1/9) -> 0.045757491
A6: V001 | B6: =COUNTIF(Payments!$C$5:$C$634,A6) -> 12 | C6: =COUNTIFS(Payments!$C$5:$C$634,$A6,Payments!$G$5:$G$634,1) -> 0 | D6: =COUNTIFS(Payments!$C$5:$C$634,$A6,Payments!$G$5:$G$634,2) -> 0 | E6: =COUNTIFS(Payments!$C$5:$C$634,$A6,Payments!$G$5:$G$634,3) -> 0 | F6: =COUNTIFS(Payments!$C$5:$C$634,$A6,Payments!$G$5:$G$634,4) -> 0 | G6: =COUNTIFS(Payments!$C$5:$C$634,$A6,Payments!$G$5:$G$634,5) -> 0 | H6: =COUNTIFS(Payments!$C$5:$C$634,$A6,Payments!$G$5:$G$634,6) -> 0 | I6: =COUNTIFS(Payments!$C$5:$C$634,$A6,Payments!$G$5:$G$634,7) -> 0 | J6: =COUNTIFS(Payments!$C$5:$C$634,$A6,Payments!$G$5:$G$634,8) -> 12 | K6: =COUNTIFS(Payments!$C$5:$C$634,$A6,Payments!$G$5:$G$634,9) -> 0 | L6: =IF(B6=0,0,SUMPRODUCT(ABS(C6:K6/B6-$C$5:$K$5))/9) -> 0.210855 | M6: =IF(AND(B6>=Parameters!$B$13,L6>Parameters!$B$14),1,0) -> 0 | N6: =IF(COUNTIF(Employees!$B$5:$B$29,INDEX(Vendors!$C$5:$C$49,MATCH(A6,Vendors!$A$5:$A$49,0)))>0,1,0) -> 0
A7: V002 | B7: =COUNTIF(Payments!$C$5:$C$634,A7) -> 12 | C7: =COUNTIFS(Payments!$C$5:$C$634,$A7,Payments!$G$5:$G$634,1) -> 0 | D7: =COUNTIFS(Payments!$C$5:$C$634,$A7,Payments!$G$5:$G$634,2) -> 0 | E7: =COUNTIFS(Payments!$C$5:$C$634,$A7,Payments!$G$5:$G$634,3) -> 0 | F7: =COUNTIFS(Payments!$C$5:$C$634,$A7,Payments!$G$5:$G$634,4) -> 12 | G7: =COUNTIFS(Payments!$C$5:$C$634,$A7,Payments!$G$5:$G$634,5) -> 0 | H7: =COUNTIFS(Payments!$C$5:$C$634,$A7,Payments!$G$5:$G$634,6) -> 0 | I7: =COUNTIFS(Payments!$C$5:$C$634,$A7,Payments!$G$5:$G$634,7) -> 0 | J7: =COUNTIFS(Payments!$C$5:$C$634,$A7,Payments!$G$5:$G$634,8) -> 0 | K7: =COUNTIFS(Payments!$C$5:$C$634,$A7,Payments!$G$5:$G$634,9) -> 0 | L7: =IF(B7=0,0,SUMPRODUCT(ABS(C7:K7/B7-$C$5:$K$5))/9) -> 0.20068666 | M7: =IF(AND(B7>=Parameters!$B$13,L7>Parameters!$B$14),1,0) -> 0 | N7: =IF(COUNTIF(Employees!$B$5:$B$29,INDEX(Vendors!$C$5:$C$49,MATCH(A7,Vendors!$A$5:$A$49,0)))>0,1,0) -> 0
A8: V003 | B8: =COUNTIF(Payments!$C$5:$C$634,A8) -> 16 | C8: =COUNTIFS(Payments!$C$5:$C$634,$A8,Payments!$G$5:$G$634,1) -> 7 | D8: =COUNTIFS(Payments!$C$5:$C$634,$A8,Payments!$G$5:$G$634,2) -> 3 | E8: =COUNTIFS(Payments!$C$5:$C$634,$A8,Payments!$G$5:$G$634,3) -> 2 | F8: =COUNTIFS(Payments!$C$5:$C$634,$A8,Payments!$G$5:$G$634,4) -> 3 | G8: =COUNTIFS(Payments!$C$5:$C$634,$A8,Payments!$G$5:$G$634,5) -> 0 | H8: =COUNTIFS(Payments!$C$5:$C$634,$A8,Payments!$G$5:$G$634,6) -> 1 | I8: =COUNTIFS(Payments!$C$5:$C$634,$A8,Payments!$G$5:$G$634,7) -> 0 | J8: =COUNTIFS(Payments!$C$5:$C$634,$A8,Payments!$G$5:$G$634,8) -> 0 | K8: =COUNTIFS(Payments!$C$5:$C$634,$A8,Payments!$G$5:$G$634,9) -> 0 | L8: =IF(B8=0,0,SUMPRODUCT(ABS(C8:K8/B8-$C$5:$K$5))/9) -> 0.053006666 | M8: =IF(AND(B8>=Parameters!$B$13,L8>Parameters!$B$14),1,0) -> 0 | N8: =IF(COUNTIF(Employees!$B$5:$B$29,INDEX(Vendors!$C$5:$C$49,MATCH(A8,Vendors!$A$5:$A$49,0)))>0,1,0) -> 0
A9: V004 | B9: =COUNTIF(Payments!$C$5:$C$634,A9) -> 10 | C9: =COUNTIFS(Payments!$C$5:$C$634,$A9,Payments!$G$5:$G$634,1) -> 5 | D9: =COUNTIFS(Payments!$C$5:$C$634,$A9,Payments!$G$5:$G$634,2) -> 1 | E9: =COUNTIFS(Payments!$C$5:$C$634,$A9,Payments!$G$5:$G$634,3) -> 0 | F9: =COUNTIFS(Payments!$C$5:$C$634,$A9,Payments!$G$5:$G$634,4) -> 1 | G9: =COUNTIFS(Payments!$C$5:$C$634,$A9,Payments!$G$5:$G$634,5) -> 0 | H9: =COUNTIFS(Payments!$C$5:$C$634,$A9,Payments!$G$5:$G$634,6) -> 1 | I9: =COUNTIFS(Payments!$C$5:$C$634,$A9,Payments!$G$5:$G$634,7) -> 0 | J9: =COUNTIFS(Payments!$C$5:$C$634,$A9,Payments!$G$5:$G$634,8) -> 2 | K9: =COUNTIFS(Payments!$C$5:$C$634,$A9,Payments!$G$5:$G$634,9) -> 0 | L9: =IF(B9=0,0,SUMPRODUCT(ABS(C9:K9/B9-$C$5:$K$5))/9) -> 0.085324595 | M9: =IF(AND(B9>=Parameters!$B$13,L9>Parameters!$B$14),1,0) -> 0 | N9: =IF(COUNTIF(Employees!$B$5:$B$29,INDEX(Vendors!$C$5:$C$49,MATCH(A9,Vendors!$A$5:$A$49,0)))>0,1,0) -> 0
A10: V005 | B10: =COUNTIF(Payments!$C$5:$C$634,A10) -> 18 | C10: =COUNTIFS(Payments!$C$5:$C$634,$A10,Payments!$G$5:$G$634,1) -> 4 | D10: =COUNTIFS(Payments!$C$5:$C$634,$A10,Payments!$G$5:$G$634,2) -> 6 | E10: =COUNTIFS(Payments!$C$5:$C$634,$A10,Payments!$G$5:$G$634,3) -> 5 | F10: =COUNTIFS(Payments!$C$5:$C$634,$A10,Payments!$G$5:$G$634,4) -> 0 | G10: =COUNTIFS(Payments!$C$5:$C$634,$A10,Payments!$G$5:$G$634,5) -> 2 | H10: =COUNTIFS(Payments!$C$5:$C$634,$A10,Payments!$G$5:$G$634,6) -> 0 | I10: =COUNTIFS(Payments!$C$5:$C$634,$A10,Payments!$G$5:$G$634,7) -> 0 | J10: =COUNTIFS(Payments!$C$5:$C$634,$A10,Payments!$G$5:$G$634,8) -> 0 | K10: =COUNTIFS(Payments!$C$5:$C$634,$A10,Payments!$G$5:$G$634,9) -> 1 | L10: =IF(B10=0,0,SUMPRODUCT(ABS(C10:K10/B10-$C$5:$K$5))/9) -> 0.078179788 | M10: =IF(AND(B10>=Parameters!$B$13,L10>Parameters!$B$14),1,0) -> 0 | N10: =IF(COUNTIF(Employees!$B$5:$B$29,INDEX(Vendors!$C$5:$C$49,MATCH(A10,Vendors!$A$5:$A$49,0)))>0,1,0) -> 0
A11: V006 | B11: =COUNTIF(Payments!$C$5:$C$634,A11) -> 8 | C11: =COUNTIFS(Payments!$C$5:$C$634,$A11,Payments!$G$5:$G$634,1) -> 2 | D11: =COUNTIFS(Payments!$C$5:$C$634,$A11,Payments!$G$5:$G$634,2) -> 1 | E11: =COUNTIFS(Payments!$C$5:$C$634,$A11,Payments!$G$5:$G$634,3) -> 1 | F11: =COUNTIFS(Payments!$C$5:$C$634,$A11,Payments!$G$5:$G$634,4) -> 0 | G11: =COUNTIFS(Payments!$C$5:$C$634,$A11,Payments!$G$5:$G$634,5) -> 1 | H11: =COUNTIFS(Payments!$C$5:$C$634,$A11,Payments!$G$5:$G$634,6) -> 0 | I11: =COUNTIFS(Payments!$C$5:$C$634,$A11,Payments!$G$5:$G$634,7) -> 0 | J11: =COUNTIFS(Payments!$C$5:$C$634,$A11,Payments!$G$5:$G$634,8) -> 2 | K11: =COUNTIFS(Payments!$C$5:$C$634,$A11,Payments!$G$5:$G$634,9) -> 1 | L11: =IF(B11=0,0,SUMPRODUCT(ABS(C11:K11/B11-$C$5:$K$5))/9) -> 0.071993334 | M11: =IF(AND(B11>=Parameters!$B$13,L11>Parameters!$B$14),1,0) -> 0 | N11: =IF(COUNTIF(Employees!$B$5:$B$29,INDEX(Vendors!$C$5:$C$49,MATCH(A11,Vendors!$A$5:$A$49,0)))>0,1,0) -> 0
A12: V007 | B12: =COUNTIF(Payments!$C$5:$C$634,A12) -> 16 | C12: =COUNTIFS(Payments!$C$5:$C$634,$A12,Payments!$G$5:$G$634,1) -> 5 | D12: =COUNTIFS(Payments!$C$5:$C$634,$A12,Payments!$G$5:$G$634,2) -> 5 | E12: =COUNTIFS(Payments!$C$5:$C$634,$A12,Payments!$G$5:$G$634,3) -> 2 | F12: =COUNTIFS(Payments!$C$5:$C$634,$A12,Payments!$G$5:$G$634,4) -> 1 | G12: =COUNTIFS(Payments!$C$5:$C$634,$A12,Payments!$G$5:$G$634,5) -> 0 | H12: =COUNTIFS(Payments!$C$5:$C$634,$A12,Payments!$G$5:$G$634,6) -> 2 | I12: =COUNTIFS(Payments!$C$5:$C$634,$A12,Payments!$G$5:$G$634,7) -> 1 | J12: =COUNTIFS(Payments!$C$5:$C$634,$A12,Payments!$G$5:$G$634,8) -> 0 | K12: =COUNTIFS(Payments!$C$5:$C$634,$A12,Payments!$G$5:$G$634,9) -> 0 | L12: =IF(B12=0,0,SUMPRODUCT(ABS(C12:K12/B12-$C$5:$K$5))/9) -> 0.04677806 | M12: =IF(AND(B12>=Parameters!$B$13,L12>Parameters!$B$14),1,0) -> 0 | N12: =IF(COUNTIF(Employees!$B$5:$B$29,INDEX(Vendors!$C$5:$C$49,MATCH(A12,Vendors!$A$5:$A$49,0)))>0,1,0) -> 0
A13: V008 | B13: =COUNTIF(Payments!$C$5:$C$634,A13) -> 16 | C13: =COUNTIFS(Payments!$C$5:$C$634,$A13,Payments!$G$5:$G$634,1) -> 4 | D13: =COUNTIFS(Payments!$C$5:$C$634,$A13,Payments!$G$5:$G$634,2) -> 4 | E13: =COUNTIFS(Payments!$C$5:$C$634,$A13,Payments!$G$5:$G$634,3) -> 3 | F13: =COUNTIFS(Payments!$C$5:$C$634,$A13,Payments!$G$5:$G$634,4) -> 2 | G13: =COUNTIFS(Payments!$C$5:$C$634,$A13,Payments!$G$5:$G$634,5) -> 1 | H13: =COUNTIFS(Payments!$C$5:$C$634,$A13,Payments!$G$5:$G$634,6) -> 0 | I13: =COUNTIFS(Payments!$C$5:$C$634,$A13,Payments!$G$5:$G$634,7) -> 1 | J13: =COUNTIFS(Payments!$C$5:$C$634,$A13,Payments!$G$5:$G$634,8) -> 1 | K13: =COUNTIFS(Payments!$C$5:$C$634,$A13,Payments!$G$5:$G$634,9) -> 0 | L13: =IF(B13=0,0,SUMPRODUCT(ABS(C13:K13/B13-$C$5:$K$5))/9) -> 0.040092338 | M13: =IF(AND(B13>=Parameters!$B$13,L13>Parameters!$B$14),1,0) -> 0 | N13: =IF(COUNTIF(Employees!$B$5:$B$29,INDEX(Vendors!$C$5:$C$49,MATCH(A13,Vendors!$A$5:$A$49,0)))>0,1,0) -> 0
A14: V009 | B14: =COUNTIF(Payments!$C$5:$C$634,A14) -> 27 | C14: =COUNTIFS(Payments!$C$5:$C$634,$A14,Payments!$G$5:$G$634,1) -> 7 | D14: =COUNTIFS(Payments!$C$5:$C$634,$A14,Payments!$G$5:$G$634,2) -> 8 | E14: =COUNTIFS(Payments!$C$5:$C$634,$A14,Payments!$G$5:$G$634,3) -> 4 | F14: =COUNTIFS(Payments!$C$5:$C$634,$A14,Payments!$G$5:$G$634,4) -> 3 | G14: =COUNTIFS(Payments!$C$5:$C$634,$A14,Payments!$G$5:$G$634,5) -> 1 | H14: =COUNTIFS(Payments!$C$5:$C$634,$A14,Payments!$G$5:$G$634,6) -> 2 | I14: =COUNTIFS(Payments!$C$5:$C$634,$A14,Payments!$G$5:$G$634,7) -> 1 | J14: =COUNTIFS(Payments!$C$5:$C$634,$A14,Payments!$G$5:$G$634,8) -> 0 | K14: =COUNTIFS(Payments!$C$5:$C$634,$A14,Payments!$G$5:$G$634,9) -> 1 | L14: =IF(B14=0,0,SUMPRODUCT(ABS(C14:K14/B14-$C$5:$K$5))/9) -> 0.036609518 | M14: =IF(AND(B14>=Parameters!$B$13,L14>Parameters!$B$14),1,0) -> 0 | N14: =IF(COUNTIF(Employees!$B$5:$B$29,INDEX(Vendors!$C$5:$C$49,MATCH(A14,Vendors!$A$5:$A$49,0)))>0,1,0) -> 0
A15: V010 | B15: =COUNTIF(Payments!$C$5:$C$634,A15) -> 7 | C15: =COUNTIFS(Payments!$C$5:$C$634,$A15,Payments!$G$5:$G$634,1) -> 1 | D15: =COUNTIFS(Payments!$C$5:$C$634,$A15,Payments!$G$5:$G$634,2) -> 2 | E15: =COUNTIFS(Payments!$C$5:$C$634,$A15,Payments!$G$5:$G$634,3) -> 1 | F15: =COUNTIFS(Payments!$C$5:$C$634,$A15,Payments!$G$5:$G$634,4) -> 2 | G15: =COUNTIFS(Payments!$C$5:$C$634,$A15,Payments!$G$5:$G$634,5) -> 1 | H15: =COUNTIFS(Payments!$C$5:$C$634,$A15,Payments!$G$5:$G$634,6) -> 0 | I15: =COUNTIFS(Payments!$C$5:$C$634,$A15,Payments!$G$5:$G$634,7) -> 0 | J15: =COUNTIFS(Payments!$C$5:$C$634,$A15,Payments!$G$5:$G$634,8) -> 0 | K15: =COUNTIFS(Payments!$C$5:$C$634,$A15,Payments!$G$5:$G$634,9) -> 0 | L15: =IF(B15=0,0,SUMPRODUCT(ABS(C15:K15/B15-$C$5:$K$5))/9) -> 0.084449245 | M15: =IF(AND(B15>=Parameters!$B$13,L15>Parameters!$B$14),1,0) -> 0 | N15: =IF(COUNTIF(Employees!$B$5:$B$29,INDEX(Vendors!$C$5:$C$49,MATCH(A15,Vendors!$A$5:$A$49,0)))>0,1,0) -> 0
A16: V011 | B16: =COUNTIF(Payments!$C$5:$C$634,A16) -> 20 | C16: =COUNTIFS(Payments!$C$5:$C$634,$A16,Payments!$G$5:$G$634,1) -> 8 | D16: =COUNTIFS(Payments!$C$5:$C$634,$A16,Payments!$G$5:$G$634,2) -> 3 | E16: =COUNTIFS(Payments!$C$5:$C$634,$A16,Payments!$G$5:$G$634,3) -> 0 | F16: =COUNTIFS(Payments!$C$5:$C$634,$A16,Payments!$G$5:$G$634,4) -> 2 | G16: =COUNTIFS(Payments!$C$5:$C$634,$A16,Payments!$G$5:$G$634,5) -> 1 | H16: =COUNTIFS(Payments!$C$5:$C$634,$A16,Payments!$G$5:$G$634,6) -> 0 | I16: =COUNTIFS(Payments!$C$5:$C$634,$A16,Payments!$G$5:$G$634,7) -> 2 | J16: =COUNTIFS(Payments!$C$5:$C$634,$A16,Payments!$G$5:$G$634,8) -> 2 | K16: =COUNTIFS(Payments!$C$5:$C$634,$A16,Payments!$G$5:$G$634,9) -> 2 | L16: =IF(B16=0,0,SUMPRODUCT(ABS(C16:K16/B16-$C$5:$K$5))/9) -> 0.054924007 | M16: =IF(AND(B16>=Parameters!$B$13,L16>Parameters!$B$14),1,0) -> 0 | N16: =IF(COUNTIF(Employees!$B$5:$B$29,INDEX(Vendors!$C$5:$C$49,MATCH(A16,Vendors!$A$5:$A$49,0)))>0,1,0) -> 0
A17: V012 | B17: =COUNTIF(Payments!$C$5:$C$634,A17) -> 24 | C17: =COUNTIFS(Payments!$C$5:$C$634,$A17,Payments!$G$5:$G$634,1) -> 6 | D17: =COUNTIFS(Payments!$C$5:$C$634,$A17,Payments!$G$5:$G$634,2) -> 4 | E17: =COUNTIFS(Payments!$C$5:$C$634,$A17,Payments!$G$5:$G$634,3) -> 3 | F17: =COUNTIFS(Payments!$C$5:$C$634,$A17,Payments!$G$5:$G$634,4) -> 2 | G17: =COUNTIFS(Payments!$C$5:$C$634,$A17,Payments!$G$5:$G$634,5) -> 1 | H17: =COUNTIFS(Payments!$C$5:$C$634,$A17,Payments!$G$5:$G$634,6) -> 4 | I17: =COUNTIFS(Payments!$C$5:$C$634,$A17,Payments!$G$5:$G$634,7) -> 3 | J17: =COUNTIFS(Payments!$C$5:$C$634,$A17,Payments!$G$5:$G$634,8) -> 0 | K17: =COUNTIFS(Payments!$C$5:$C$634,$A17,Payments!$G$5:$G$634,9) -> 1 | L17: =IF(B17=0,0,SUMPRODUCT(ABS(C17:K17/B17-$C$5:$K$5))/9) -> 0.037064265 | M17: =IF(AND(B17>=Parameters!$B$13,L17>Parameters!$B$14),1,0) -> 0 | N17: =IF(COUNTIF(Employees!$B$5:$B$29,INDEX(Vendors!$C$5:$C$49,MATCH(A17,Vendors!$A$5:$A$49,0)))>0,1,0) -> 0
... A50: V045 | B50: =COUNTIF(Payments!$C$5:$C$634,A50) -> 11 | C50: =COUNTIFS(Payments!$C$5:$C$634,$A50,Payments!$G$5:$G$634,1) -> 5 | D50: =COUNTIFS(Payments!$C$5:$C$634,$A50,Payments!$G$5:$G$634,2) -> 2 | E50: =COUNTIFS(Payments!$C$5:$C$634,$A50,Payments!$G$5:$G$634,3) -> 1 | F50: =COUNTIFS(Payments!$C$5:$C$634,$A50,Payments!$G$5:$G$634,4) -> 0 | G50: =COUNTIFS(Payments!$C$5:$C$634,$A50,Payments!$G$5:$G$634,5) -> 0 | H50: =COUNTIFS(Payments!$C$5:$C$634,$A50,Payments!$G$5:$G$634,6) -> 0 | I50: =COUNTIFS(Payments!$C$5:$C$634,$A50,Payments!$G$5:$G$634,7) -> 1 | J50: =COUNTIFS(Payments!$C$5:$C$634,$A50,Payments!$G$5:$G$634,8) -> 1 | K50: =COUNTIFS(Payments!$C$5:$C$634,$A50,Payments!$G$5:$G$634,9) -> 1 | L50: =IF(B50=0,0,SUMPRODUCT(ABS(C50:K50/B50-$C$5:$K$5))/9) -> 0.061570599 | M50: =IF(AND(B50>=Parameters!$B$13,L50>Parameters!$B$14),1,0) -> 0 | N50: =IF(COUNTIF(Employees!$B$5:$B$29,INDEX(Vendors!$C$5:$C$49,MATCH(A50,Vendors!$A$5:$A$49,0)))>0,1,0) -> 0

Sheet COA
A1: Chart of accounts
A2: Sample / demonstration data only. No real company, vendor, employee or transaction.
A3: Synthetic.
A4: Account | B4: Name | C4: Class
A5: 1000 | B5: Cash at bank | C5: Asset
A6: 1100 | B6: Trade receivables | C6: Asset
A7: 1200 | B7: Inventory | C7: Asset
A8: 1500 | B8: Fixed assets | C8: Asset
A9: 2000 | B9: Trade payables | C9: Liability
A10: 2100 | B10: Accruals | C10: Liability
A11: 2500 | B11: Loans | C11: Liability
A12: 4000 | B12: Sales revenue | C12: Revenue
A13: 4100 | B13: Other income | C13: Revenue
A14: 5000 | B14: Cost of sales | C14: Expense
A15: 6000 | B15: Salaries | C15: Expense
A16: 6100 | B16: Rent | C16: Expense
... A19: 9999 | B19: Suspense | C19: Suspense

Sheet JE_Lines
A1: Journal entry lines
A2: Sample / demonstration data only. No real company, vendor, employee or transaction.
A3: Inputs in blue. Class is a formula.
A4: Line ID | B4: JE no | C4: Posting date | D4: Document date | E4: Account | F4: Class | G4: Debit (USD) | H4: Credit (USD) | I4: User | J4: Source | K4: Description
A5: L00001 | B5: 1001 | C5: 45658 | D5: 45657 | E5: 1000 | F5: =INDEX(COA!$C$5:$C$19,MATCH(E5,COA!$A$5:$A$19,0)) -> Asset | G5: 4474.19 | H5: 0 | I5: SYS_AR | J5: System | K5: Customer receipts
A6: L00002 | B6: 1001 | C6: 45658 | D6: 45657 | E6: 1100 | F6: =INDEX(COA!$C$5:$C$19,MATCH(E6,COA!$A$5:$A$19,0)) -> Asset | G6: 0 | H6: 4474.19 | I6: SYS_AR | J6: System | K6: Customer receipts
A7: L00003 | B7: 1002 | C7: 45658 | D7: 45656 | E7: 1100 | F7: =INDEX(COA!$C$5:$C$19,MATCH(E7,COA!$A$5:$A$19,0)) -> Asset | G7: 2895.32 | H7: 0 | I7: SYS_AR | J7: System | K7: Sales invoice batch
A8: L00004 | B8: 1002 | C8: 45658 | D8: 45656 | E8: 4000 | F8: =INDEX(COA!$C$5:$C$19,MATCH(E8,COA!$A$5:$A$19,0)) -> Revenue | G8: 0 | H8: 2895.32 | I8: SYS_AR | J8: System | K8: Sales invoice batch
A9: L00005 | B9: 1003 | C9: 45658 | D9: 45655 | E9: 1100 | F9: =INDEX(COA!$C$5:$C$19,MATCH(E9,COA!$A$5:$A$19,0)) -> Asset | G9: 9816.58 | H9: 0 | I9: SYS_AR | J9: System | K9: Sales invoice batch
A10: L00006 | B10: 1003 | C10: 45658 | D10: 45655 | E10: 1100 | F10: =INDEX(COA!$C$5:$C$19,MATCH(E10,COA!$A$5:$A$19,0)) -> Asset | G10: 4207.11 | H10: 0 | I10: SYS_AR | J10: System | K10: Sales invoice batch
A11: L00007 | B11: 1003 | C11: 45658 | D11: 45655 | E11: 4000 | F11: =INDEX(COA!$C$5:$C$19,MATCH(E11,COA!$A$5:$A$19,0)) -> Revenue | G11: 0 | H11: 14023.69 | I11: SYS_AR | J11: System | K11: Sales invoice batch
A12: L00008 | B12: 1004 | C12: 45659 | D12: 45657 | E12: 1100 | F12: =INDEX(COA!$C$5:$C$19,MATCH(E12,COA!$A$5:$A$19,0)) -> Asset | G12: 1008.74 | H12: 0 | I12: SYS_AR | J12: System | K12: Sales invoice batch
A13: L00009 | B13: 1004 | C13: 45659 | D13: 45657 | E13: 4000 | F13: =INDEX(COA!$C$5:$C$19,MATCH(E13,COA!$A$5:$A$19,0)) -> Revenue | G13: 0 | H13: 1008.74 | I13: SYS_AR | J13: System | K13: Sales invoice batch
A14: L00010 | B14: 1005 | C14: 45659 | D14: 45656 | E14: 6900 | F14: =INDEX(COA!$C$5:$C$19,MATCH(E14,COA!$A$5:$A$19,0)) -> Expense | G14: 233.11 | H14: 0 | I14: FIN02 | J14: Manual | K14: Accrual for sundry costs
A15: L00011 | B15: 1005 | C15: 45659 | D15: 45656 | E15: 2100 | F15: =INDEX(COA!$C$5:$C$19,MATCH(E15,COA!$A$5:$A$19,0)) -> Liability | G15: 0 | H15: 233.11 | I15: FIN02 | J15: Manual | K15: Accrual for sundry costs
A16: L00012 | B16: 1006 | C16: 45659 | D16: 45659 | E16: 6900 | F16: =INDEX(COA!$C$5:$C$19,MATCH(E16,COA!$A$5:$A$19,0)) -> Expense | G16: 37000 | H16: 0 | I16: FIN01 | J16: Manual | K16: Round accrual 3
... A77: L00073 | B77: 1032 | C77: 45674 | D77: 45672 | E77: 2000 | F77: =INDEX(COA!$C$5:$C$19,MATCH(E77,COA!$A$5:$A$19,0)) -> Liability | G77: 0 | H77: 12219.41 | I77: SYS_AP | J77: System | K77: Supplier invoices
A78: L00074 | B78: 1033 | C78: 45674 | D78: 45674 | E78: 6900 | F78: =INDEX(COA!$C$5:$C$19,MATCH(E78,COA!$A$5:$A$19,0)) -> Expense | G78: 34428.78 | H78: 0 | I78: FIN03 | J78: Manual
A79: L00075 | B79: 1033 | C79: 45674 | D79: 45674 | E79: 2100 | F79: =INDEX(COA!$C$5:$C$19,MATCH(E79,COA!$A$5:$A$19,0)) -> Liability | G79: 0 | H79: 34428.78 | I79: FIN03 | J79: Manual
A80: L00076 | B80: 1034 | C80: 45674 | D80: 45670 | E80: 6900 | F80: =INDEX(COA!$C$5:$C$19,MATCH(E80,COA!$A$5:$A$19,0)) -> Expense | G80: 71785.26 | H80: 0 | I80: FIN01 | J80: Manual | K80: Accrual for sundry costs
A81: L00077 | B81: 1034 | C81: 45674 | D81: 45670 | E81: 2100 | F81: =INDEX(COA!$C$5:$C$19,MATCH(E81,COA!$A$5:$A$19,0)) -> Liability | G81: 0 | H81: 71785.26 | I81: FIN01 | J81: Manual | K81: Accrual for sundry costs
A82: L00078 | B82: 1035 | C82: 45674 | D82: 45672 | E82: 1000 | F82: =INDEX(COA!$C$5:$C$19,MATCH(E82,COA!$A$5:$A$19,0)) -> Asset | G82: 111700.56 | H82: 0 | I82: SYS_AR | J82: System | K82: Customer receipts
A83: L00079 | B83: 1035 | C83: 45674 | D83: 45672 | E83: 1100 | F83: =INDEX(COA!$C$5:$C$19,MATCH(E83,COA!$A$5:$A$19,0)) -> Asset | G83: 0 | H83: 111700.56 | I83: SYS_AR | J83: System | K83: Customer receipts
A84: L00080 | B84: 1036 | C84: 45674 | D84: 45670 | E84: 5000 | F84: =INDEX(COA!$C$5:$C$19,MATCH(E84,COA!$A$5:$A$19,0)) -> Expense | G84: 9230.62 | H84: 0 | I84: SYS_AR | J84: System | K84: Cost of sales posting
A85: L00081 | B85: 1036 | C85: 45674 | D85: 45670 | E85: 1200 | F85: =INDEX(COA!$C$5:$C$19,MATCH(E85,COA!$A$5:$A$19,0)) -> Asset | G85: 0 | H85: 9230.62 | I85: SYS_AR | J85: System | K85: Cost of sales posting
A86: L00082 | B86: 1037 | C86: 45674 | D86: 45674 | E86: 5000 | F86: =INDEX(COA!$C$5:$C$19,MATCH(E86,COA!$A$5:$A$19,0)) -> Expense | G86: 4993.54 | H86: 0 | I86: SYS_AR | J86: System | K86: Cost of sales posting
A87: L00083 | B87: 1037 | C87: 45674 | D87: 45674 | E87: 1200 | F87: =INDEX(COA!$C$5:$C$19,MATCH(E87,COA!$A$5:$A$19,0)) -> Asset | G87: 0 | H87: 4993.54 | I87: SYS_AR | J87: System | K87: Cost of sales posting
A88: L00084 | B88: 1038 | C88: 45675 | D88: 45672 | E88: 2000 | F88: =INDEX(COA!$C$5:$C$19,MATCH(E88,COA!$A$5:$A$19,0)) -> Liability | G88: 27029.59 | H88: 0 | I88: SYS_PAY | J88: System | K88: Supplier payments
A89: L00085 | B89: 1038 | C89: 45675 | D89: 45672 | E89: 1000 | F89: =INDEX(COA!$C$5:$C$19,MATCH(E89,COA!$A$5:$A$19,0)) -> Asset | G89: 0 | H89: 27029.59 | I89: SYS_PAY | J89: System | K89: Supplier payments
A90: L00086 | B90: 1039 | C90: 45677 | D90: 45676 | E90: 1000 | F90: =INDEX(COA!$C$5:$C$19,MATCH(E90,COA!$A$5:$A$19,0)) -> Asset | G90: 558.57 | H90: 0 | I90: SYS_AR | J90: System | K90: Customer receipts
A91: L00087 | B91: 1039 | C91: 45677 | D91: 45676 | E91: 1000 | F91: =INDEX(COA!$C$5:$C$19,MATCH(E91,COA!$A$5:$A$19,0)) -> Asset | G91: 239.39 | H91: 0 | I91: SYS_AR | J91: System | K91: Customer receipts
... A120: L00116 | B120: 1052 | C120: 45680 | D120: 45678 | E120: 1100 | F120: =INDEX(COA!$C$5:$C$19,MATCH(E120,COA!$A$5:$A$19,0)) -> Asset | G120: 0 | H120: 70722.06 | I120: SYS_AR | J120: System | K120: Customer receipts
A121: L00117 | B121: 1053 | C121: 45680 | D121: 45680 | E121: 1000 | F121: =INDEX(COA!$C$5:$C$19,MATCH(E121,COA!$A$5:$A$19,0)) -> Asset | G121: 44483.01 | H121: 0 | I121: SYS_AR | J121: System
A122: L00118 | B122: 1053 | C122: 45680 | D122: 45680 | E122: 1100 | F122: =INDEX(COA!$C$5:$C$19,MATCH(E122,COA!$A$5:$A$19,0)) -> Asset | G122: 0 | H122: 44483.01 | I122: SYS_AR | J122: System
A123: L00119 | B123: 1054 | C123: 45681 | D123: 45678 | E123: 1100 | F123: =INDEX(COA!$C$5:$C$19,MATCH(E123,COA!$A$5:$A$19,0)) -> Asset | G123: 1513.51 | H123: 0 | I123: SYS_AR | J123: System | K123: Sales invoice batch
A124: L00120 | B124: 1054 | C124: 45681 | D124: 45678 | E124: 4000 | F124: =INDEX(COA!$C$5:$C$19,MATCH(E124,COA!$A$5:$A$19,0)) -> Revenue | G124: 0 | H124: 1513.51 | I124: SYS_AR | J124: System | K124: Sales invoice batch
A125: L00121 | B125: 1055 | C125: 45681 | D125: 45681 | E125: 2100 | F125: =INDEX(COA!$C$5:$C$19,MATCH(E125,COA!$A$5:$A$19,0)) -> Liability | G125: 366.88 | H125: 0 | I125: FIN05 | J125: Manual | K125: Accrual reversal
A126: L00122 | B126: 1055 | C126: 45681 | D126: 45681 | E126: 6900 | F126: =INDEX(COA!$C$5:$C$19,MATCH(E126,COA!$A$5:$A$19,0)) -> Expense | G126: 0 | H126: 366.88 | I126: FIN05 | J126: Manual | K126: Accrual reversal
A127: L00123 | B127: 1056 | C127: 45681 | D127: 45678 | E127: 1100 | F127: =INDEX(COA!$C$5:$C$19,MATCH(E127,COA!$A$5:$A$19,0)) -> Asset | G127: 824.81 | H127: 0 | I127: SYS_AR | J127: System | K127: Sales invoice batch
A128: L00124 | B128: 1056 | C128: 45681 | D128: 45678 | E128: 4000 | F128: =INDEX(COA!$C$5:$C$19,MATCH(E128,COA!$A$5:$A$19,0)) -> Revenue | G128: 0 | H128: 824.81 | I128: SYS_AR | J128: System | K128: Sales invoice batch
A129: L00125 | B129: 1057 | C129: 45681 | D129: 45680 | E129: 2100 | F129: =INDEX(COA!$C$5:$C$19,MATCH(E129,COA!$A$5:$A$19,0)) -> Liability | G129: 50153.36 | H129: 0 | I129: FIN01 | J129: Manual | K129: Accrual reversal
A130: L00126 | B130: 1057 | C130: 45681 | D130: 45680 | E130: 6900 | F130: =INDEX(COA!$C$5:$C$19,MATCH(E130,COA!$A$5:$A$19,0)) -> Expense | G130: 0 | H130: 50153.36 | I130: FIN01 | J130: Manual | K130: Accrual reversal
A131: L00127 | B131: 1058 | C131: 45684 | D131: 45684 | E131: 6000 | F131: =INDEX(COA!$C$5:$C$19,MATCH(E131,COA!$A$5:$A$19,0)) -> Expense | G131: 254000 | H131: 0 | I131: SYS_PAY | J131: System | K131: Monthly payroll
A132: L00128 | B132: 1058 | C132: 45684 | D132: 45684 | E132: 1000 | F132: =INDEX(COA!$C$5:$C$19,MATCH(E132,COA!$A$5:$A$19,0)) -> Asset | G132: 0 | H132: 254000 | I132: SYS_PAY | J132: System | K132: Monthly payroll
A133: L00129 | B133: 1059 | C133: 45684 | D133: 45682 | E133: 1500 | F133: =INDEX(COA!$C$5:$C$19,MATCH(E133,COA!$A$5:$A$19,0)) -> Asset | G133: 1877.82 | H133: 0 | I133: SYS_AP | J133: System | K133: Fixed asset additions
A134: L00130 | B134: 1059 | C134: 45684 | D134: 45682 | E134: 2000 | F134: =INDEX(COA!$C$5:$C$19,MATCH(E134,COA!$A$5:$A$19,0)) -> Liability | G134: 0 | H134: 1877.82 | I134: SYS_AP | J134: System | K134: Fixed asset additions
... A157: L00153 | B157: 1071 | C157: 45686 | D157: 45686 | E157: 4000 | F157: =INDEX(COA!$C$5:$C$19,MATCH(E157,COA!$A$5:$A$19,0)) -> Revenue | G157: 0 | H157: 22822.3 | I157: SYS_AR | J157: System | K157: Sales invoice batch
A158: L00154 | B158: 1072 | C158: 45686 | D158: 45686 | E158: 6900 | F158: =INDEX(COA!$C$5:$C$19,MATCH(E158,COA!$A$5:$A$19,0)) -> Expense | G158: 628.29 | H158: 0 | I158: FIN02 | J158: Manual
A159: L00155 | B159: 1072 | C159: 45686 | D159: 45686 | E159: 2100 | F159: =INDEX(COA!$C$5:$C$19,MATCH(E159,COA!$A$5:$A$19,0)) -> Liability | G159: 0 | H159: 628.29 | I159: FIN02 | J159: Manual
A160: L00156 | B160: 1073 | C160: 45687 | D160: 45683 | E160: 5000 | F160: =INDEX(COA!$C$5:$C$19,MATCH(E160,COA!$A$5:$A$19,0)) -> Expense | G160: 842.62 | H160: 0 | I160: SYS_AR | J160: System | K160: Cost of sales posting
A161: L00157 | B161: 1073 | C161: 45687 | D161: 45683 | E161: 1200 | F161: =INDEX(COA!$C$5:$C$19,MATCH(E161,COA!$A$5:$A$19,0)) -> Asset | G161: 0 | H161: 842.62 | I161: SYS_AR | J161: System | K161: Cost of sales posting
A162: L00158 | B162: 1074 | C162: 45687 | D162: 45685 | E162: 2000 | F162: =INDEX(COA!$C$5:$C$19,MATCH(E162,COA!$A$5:$A$19,0)) -> Liability | G162: 15545.09 | H162: 0 | I162: SYS_PAY | J162: System | K162: Supplier payments
A163: L00159 | B163: 1074 | C163: 45687 | D163: 45685 | E163: 1000 | F163: =INDEX(COA!$C$5:$C$19,MATCH(E163,COA!$A$5:$A$19,0)) -> Asset | G163: 0 | H163: 15545.09 | I163: SYS_PAY | J163: System | K163: Supplier payments
A164: L00160 | B164: 1078 | C164: 45687 | D164: 45686 | E164: 1000 | F164: =INDEX(COA!$C$5:$C$19,MATCH(E164,COA!$A$5:$A$19,0)) -> Asset | G164: 16301.44 | H164: 0 | I164: SYS_AR | J164: System | K164: Customer receipts
A165: L00161 | B165: 1078 | C165: 45687 | D165: 45686 | E165: 1100 | F165: =INDEX(COA!$C$5:$C$19,MATCH(E165,COA!$A$5:$A$19,0)) -> Asset | G165: 0 | H165: 16301.44 | I165: SYS_AR | J165: System | K165: Customer receipts
A166: L00162 | B166: 1079 | C166: 45688 | D166: 45684 | E166: 1100 | F166: =INDEX(COA!$C$5:$C$19,MATCH(E166,COA!$A$5:$A$19,0)) -> Asset | G166: 325.45 | H166: 0 | I166: SYS_AR | J166: System | K166: Sales invoice batch
A167: L00163 | B167: 1079 | C167: 45688 | D167: 45684 | E167: 1100 | F167: =INDEX(COA!$C$5:$C$19,MATCH(E167,COA!$A$5:$A$19,0)) -> Asset | G167: 139.48 | H167: 0 | I167: SYS_AR | J167: System | K167: Sales invoice batch
A168: L00164 | B168: 1079 | C168: 45688 | D168: 45684 | E168: 4000 | F168: =INDEX(COA!$C$5:$C$19,MATCH(E168,COA!$A$5:$A$19,0)) -> Revenue | G168: 0 | H168: 464.93 | I168: SYS_AR | J168: System | K168: Sales invoice batch
A169: L00165 | B169: 1080 | C169: 45688 | D169: 45687 | E169: 1500 | F169: =INDEX(COA!$C$5:$C$19,MATCH(E169,COA!$A$5:$A$19,0)) -> Asset | G169: 471.15 | H169: 0 | I169: SYS_AP | J169: System | K169: Fixed asset additions
A170: L00166 | B170: 1080 | C170: 45688 | D170: 45687 | E170: 2000 | F170: =INDEX(COA!$C$5:$C$19,MATCH(E170,COA!$A$5:$A$19,0)) -> Liability | G170: 0 | H170: 471.15 | I170: SYS_AP | J170: System | K170: Fixed asset additions
A171: L00167 | B171: 1081 | C171: 45691 | D171: 45691 | E171: 1000 | F171: =INDEX(COA!$C$5:$C$19,MATCH(E171,COA!$A$5:$A$19,0)) -> Asset | G171: 3846.75 | H171: 0 | I171: SYS_AR | J171: System | K171: Customer receipts
... A255: L00251 | B255: 1120 | C255: 45706 | D255: 45702 | E255: 4000 | F255: =INDEX(COA!$C$5:$C$19,MATCH(E255,COA!$A$5:$A$19,0)) -> Revenue | G255: 0 | H255: 7674.41 | I255: SYS_AR | J255: System | K255: Sales invoice batch
A256: L00252 | B256: 1121 | C256: 45706 | D256: 45703 | E256: 5000 | F256: =INDEX(COA!$C$5:$C$19,MATCH(E256,COA!$A$5:$A$19,0)) -> Expense | G256: 9102.03 | H256: 0 | I256: SYS_AR | J256: System
A257: L00253 | B257: 1121 | C257: 45706 | D257: 45703 | E257: 5000 | F257: =INDEX(COA!$C$5:$C$19,MATCH(E257,COA!$A$5:$A$19,0)) -> Expense | G257: 3900.87 | H257: 0 | I257: SYS_AR | J257: System
A258: L00254 | B258: 1121 | C258: 45706 | D258: 45703 | E258: 1200 | F258: =INDEX(COA!$C$5:$C$19,MATCH(E258,COA!$A$5:$A$19,0)) -> Asset | G258: 0 | H258: 13002.9 | I258: SYS_AR | J258: System
A259: L00255 | B259: 1122 | C259: 45706 | D259: 45704 | E259: 1100 | F259: =INDEX(COA!$C$5:$C$19,MATCH(E259,COA!$A$5:$A$19,0)) -> Asset | G259: 32026.95 | H259: 0 | I259: SYS_AR | J259: System | K259: Sales invoice batch
A260: L00256 | B260: 1122 | C260: 45706 | D260: 45704 | E260: 4000 | F260: =INDEX(COA!$C$5:$C$19,MATCH(E260,COA!$A$5:$A$19,0)) -> Revenue | G260: 0 | H260: 32026.95 | I260: SYS_AR | J260: System | K260: Sales invoice batch
A261: L00257 | B261: 1123 | C261: 45707 | D261: 45704 | E261: 2000 | F261: =INDEX(COA!$C$5:$C$19,MATCH(E261,COA!$A$5:$A$19,0)) -> Liability | G261: 449.01 | H261: 0 | I261: SYS_PAY | J261: System | K261: Supplier payments
A262: L00258 | B262: 1123 | C262: 45707 | D262: 45704 | E262: 1000 | F262: =INDEX(COA!$C$5:$C$19,MATCH(E262,COA!$A$5:$A$19,0)) -> Asset | G262: 0 | H262: 449.01 | I262: SYS_PAY | J262: System | K262: Supplier payments
A263: L00259 | B263: 1124 | C263: 45707 | D263: 45707 | E263: 6900 | F263: =INDEX(COA!$C$5:$C$19,MATCH(E263,COA!$A$5:$A$19,0)) -> Expense | G263: 765.54 | H263: 0 | I263: FIN05 | J263: Manual | K263: Adjustment 1
A264: L00260 | B264: 1124 | C264: 45707 | D264: 45707 | E264: 2100 | F264: =INDEX(COA!$C$5:$C$19,MATCH(E264,COA!$A$5:$A$19,0)) -> Liability | G264: 0 | H264: 865.54 | I264: FIN05 | J264: Manual | K264: Adjustment 1
A265: L00261 | B265: 1125 | C265: 45707 | D265: 45703 | E265: 1100 | F265: =INDEX(COA!$C$5:$C$19,MATCH(E265,COA!$A$5:$A$19,0)) -> Asset | G265: 1637.22 | H265: 0 | I265: SYS_AR | J265: System | K265: Sales invoice batch
A266: L00262 | B266: 1125 | C266: 45707 | D266: 45703 | E266: 4000 | F266: =INDEX(COA!$C$5:$C$19,MATCH(E266,COA!$A$5:$A$19,0)) -> Revenue | G266: 0 | H266: 1637.22 | I266: SYS_AR | J266: System | K266: Sales invoice batch
A267: L00263 | B267: 1126 | C267: 45708 | D267: 45705 | E267: 1000 | F267: =INDEX(COA!$C$5:$C$19,MATCH(E267,COA!$A$5:$A$19,0)) -> Asset | G267: 846.22 | H267: 0 | I267: SYS_AR | J267: System | K267: Customer receipts
A268: L00264 | B268: 1126 | C268: 45708 | D268: 45705 | E268: 1100 | F268: =INDEX(COA!$C$5:$C$19,MATCH(E268,COA!$A$5:$A$19,0)) -> Asset | G268: 0 | H268: 846.22 | I268: SYS_AR | J268: System | K268: Customer receipts
A269: L00265 | B269: 1127 | C269: 45708 | D269: 45708 | E269: 6900 | F269: =INDEX(COA!$C$5:$C$19,MATCH(E269,COA!$A$5:$A$19,0)) -> Expense | G269: 50670.9 | H269: 0 | I269: TEMP02 | J269: Manual | K269: Manual journal 1
A270: L00266 | B270: 1127 | C270: 45708 | D270: 45708 | E270: 2100 | F270: =INDEX(COA!$C$5:$C$19,MATCH(E270,COA!$A$5:$A$19,0)) -> Liability | G270: 0 | H270: 50670.9 | I270: TEMP02 | J270: Manual | K270: Manual journal 1
... A413: L00409 | B413: 1194 | C413: 45736 | D413: 45734 | E413: 2000 | F413: =INDEX(COA!$C$5:$C$19,MATCH(E413,COA!$A$5:$A$19,0)) -> Liability | G413: 0 | H413: 64403.3 | I413: SYS_AP | J413: System | K413: Supplier invoices
A414: L00410 | B414: 1195 | C414: 45736 | D414: 45733 | E414: 6200 | F414: =INDEX(COA!$C$5:$C$19,MATCH(E414,COA!$A$5:$A$19,0)) -> Expense | G414: 13475.25 | H414: 0 | I414: SYS_AP | J414: System
A415: L00411 | B415: 1195 | C415: 45736 | D415: 45733 | E415: 6200 | F415: =INDEX(COA!$C$5:$C$19,MATCH(E415,COA!$A$5:$A$19,0)) -> Expense | G415: 5775.11 | H415: 0 | I415: SYS_AP | J415: System
A416: L00412 | B416: 1195 | C416: 45736 | D416: 45733 | E416: 2000 | F416: =INDEX(COA!$C$5:$C$19,MATCH(E416,COA!$A$5:$A$19,0)) -> Liability | G416: 0 | H416: 19250.36 | I416: SYS_AP | J416: System
A417: L00413 | B417: 1196 | C417: 45736 | D417: 45733 | E417: 5000 | F417: =INDEX(COA!$C$5:$C$19,MATCH(E417,COA!$A$5:$A$19,0)) -> Expense | G417: 3204.52 | H417: 0 | I417: SYS_AR | J417: System | K417: Cost of sales posting
A418: L00414 | B418: 1196 | C418: 45736 | D418: 45733 | E418: 1200 | F418: =INDEX(COA!$C$5:$C$19,MATCH(E418,COA!$A$5:$A$19,0)) -> Asset | G418: 0 | H418: 3204.52 | I418: SYS_AR | J418: System | K418: Cost of sales posting
A419: L00415 | B419: 1197 | C419: 45736 | D419: 45733 | E419: 1100 | F419: =INDEX(COA!$C$5:$C$19,MATCH(E419,COA!$A$5:$A$19,0)) -> Asset | G419: 74350.97 | H419: 0 | I419: SYS_AR | J419: System | K419: Sales invoice batch
A420: L00416 | B420: 1197 | C420: 45736 | D420: 45733 | E420: 4000 | F420: =INDEX(COA!$C$5:$C$19,MATCH(E420,COA!$A$5:$A$19,0)) -> Revenue | G420: 0 | H420: 74350.97 | I420: SYS_AR | J420: System | K420: Sales invoice batch
A421: L00417 | B421: 1198 | C421: 45736 | D421: 45735 | E421: 5000 | F421: =INDEX(COA!$C$5:$C$19,MATCH(E421,COA!$A$5:$A$19,0)) -> Expense | G421: 213.17 | H421: 0 | I421: SYS_AR | J421: System | K421: Cost of sales posting
A422: L00418 | B422: 1198 | C422: 45736 | D422: 45735 | E422: 1200 | F422: =INDEX(COA!$C$5:$C$19,MATCH(E422,COA!$A$5:$A$19,0)) -> Asset | G422: 0 | H422: 213.17 | I422: SYS_AR | J422: System | K422: Cost of sales posting
A423: L00419 | B423: 1199 | C423: 45737 | D423: 45736 | E423: 1100 | F423: =INDEX(COA!$C$5:$C$19,MATCH(E423,COA!$A$5:$A$19,0)) -> Asset | G423: 220.28 | H423: 0 | I423: SYS_AR | J423: System | K423: Sales invoice batch
A424: L00420 | B424: 1199 | C424: 45737 | D424: 45736 | E424: 4000 | F424: =INDEX(COA!$C$5:$C$19,MATCH(E424,COA!$A$5:$A$19,0)) -> Revenue | G424: 0 | H424: 220.28 | I424: SYS_AR | J424: System | K424: Sales invoice batch
A425: L00421 | B425: 1200 | C425: 45737 | D425: 45737 | E425: 5000 | F425: =INDEX(COA!$C$5:$C$19,MATCH(E425,COA!$A$5:$A$19,0)) -> Expense | G425: 206.09 | H425: 0 | I425: SYS_AR | J425: System | K425: Cost of sales posting
A426: L00422 | B426: 1200 | C426: 45737 | D426: 45737 | E426: 5000 | F426: =INDEX(COA!$C$5:$C$19,MATCH(E426,COA!$A$5:$A$19,0)) -> Expense | G426: 88.32 | H426: 0 | I426: SYS_AR | J426: System | K426: Cost of sales posting
A427: L00423 | B427: 1200 | C427: 45737 | D427: 45737 | E427: 1200 | F427: =INDEX(COA!$C$5:$C$19,MATCH(E427,COA!$A$5:$A$19,0)) -> Asset | G427: 0 | H427: 294.41 | I427: SYS_AR | J427: System | K427: Cost of sales posting
A428: L00424 | B428: 1201 | C428: 45737 | D428: 45736 | E428: 5000 | F428: =INDEX(COA!$C$5:$C$19,MATCH(E428,COA!$A$5:$A$19,0)) -> Expense | G428: 4879.69 | H428: 0 | I428: SYS_AR | J428: System | K428: Cost of sales posting
... A535: L00531 | B535: 1249 | C535: 45771 | D535: 45769 | E535: 1000 | F535: =INDEX(COA!$C$5:$C$19,MATCH(E535,COA!$A$5:$A$19,0)) -> Asset | G535: 0 | H535: 15205.81 | I535: SYS_PAY | J535: System | K535: Supplier payments
A536: L00532 | B536: 1250 | C536: 45772 | D536: 45772 | E536: 6900 | F536: =INDEX(COA!$C$5:$C$19,MATCH(E536,COA!$A$5:$A$19,0)) -> Expense | G536: 3695.87 | H536: 0 | I536: FIN05 | J536: Manual
A537: L00533 | B537: 1250 | C537: 45772 | D537: 45772 | E537: 2100 | F537: =INDEX(COA!$C$5:$C$19,MATCH(E537,COA!$A$5:$A$19,0)) -> Liability | G537: 0 | H537: 3695.87 | I537: FIN05 | J537: Manual
A538: L00534 | B538: 1251 | C538: 45772 | D538: 45768 | E538: 2000 | F538: =INDEX(COA!$C$5:$C$19,MATCH(E538,COA!$A$5:$A$19,0)) -> Liability | G538: 586.14 | H538: 0 | I538: SYS_PAY | J538: System | K538: Supplier payments
A539: L00535 | B539: 1251 | C539: 45772 | D539: 45768 | E539: 1000 | F539: =INDEX(COA!$C$5:$C$19,MATCH(E539,COA!$A$5:$A$19,0)) -> Asset | G539: 0 | H539: 586.14 | I539: SYS_PAY | J539: System | K539: Supplier payments
A540: L00536 | B540: 1252 | C540: 45772 | D540: 45769 | E540: 1000 | F540: =INDEX(COA!$C$5:$C$19,MATCH(E540,COA!$A$5:$A$19,0)) -> Asset | G540: 76955.59 | H540: 0 | I540: SYS_AR | J540: System | K540: Customer receipts
A541: L00537 | B541: 1252 | C541: 45772 | D541: 45769 | E541: 1100 | F541: =INDEX(COA!$C$5:$C$19,MATCH(E541,COA!$A$5:$A$19,0)) -> Asset | G541: 0 | H541: 76955.59 | I541: SYS_AR | J541: System | K541: Customer receipts
...

Sheet JE_Entries
A1: Journal entry tests, one row per entry
A2: Sample / demonstration data only. No real company, vendor, employee or transaction.
A3: JE number is from the engine (brown). All other columns are formulas.
A4: JE no | B4: Lines | C4: Total debit | D4: Total credit | E4: Debit less credit | F4: Posting date | G4: Document date | H4: User | I4: Source | J4: Description | K4: Lag (days) | L4: Revenue lines | M4: Suspense lines | N4: Unbalanced | O4: Weekend | P4: Late posting | Q4: Year end window | R4: Unauthorised user | S4: Manual to revenue | T4: Round total | U4: No description | V4: Below limit | W4: Manual to suspense | X4: Sequence gap | Y4: Risk score | Z4: Priority
A5: 1001 | B5: =COUNTIF(JE_Lines!$B$5:$B$1733,A5) -> 2 | C5: =SUMIFS(JE_Lines!$G$5:$G$1733,JE_Lines!$B$5:$B$1733,A5) -> 4474.19 | D5: =SUMIFS(JE_Lines!$H$5:$H$1733,JE_Lines!$B$5:$B$1733,A5) -> 4474.19 | E5: =C5-D5 -> 0 | F5: =INDEX(JE_Lines!$C$5:$C$1733,MATCH(A5,JE_Lines!$B$5:$B$1733,0)) -> 45658 | G5: =INDEX(JE_Lines!$D$5:$D$1733,MATCH(A5,JE_Lines!$B$5:$B$1733,0)) -> 45657 | H5: =INDEX(JE_Lines!$I$5:$I$1733,MATCH(A5,JE_Lines!$B$5:$B$1733,0)) -> SYS_AR | I5: =INDEX(JE_Lines!$J$5:$J$1733,MATCH(A5,JE_Lines!$B$5:$B$1733,0)) -> System | J5: =IF(LEN(INDEX(JE_Lines!$K$5:$K$1733,MATCH(A5,JE_Lines!$B$5:$B$1733,0)))=0,"",INDEX(JE_Lines!$K$5:$K$1733,MATCH(A5,JE_Lines!$B$5:$B$1733,0))) -> Customer receipts | K5: =F5-G5 -> 1 | L5: =COUNTIFS(JE_Lines!$B$5:$B$1733,A5,JE_Lines!$F$5:$F$1733,"Revenue") -> 0 | M5: =COUNTIFS(JE_Lines!$B$5:$B$1733,A5,JE_Lines!$F$5:$F$1733,"Suspense") -> 0 | N5: =IF(ABS(E5)>Parameters!$B$23,1,0) -> 0 | O5: =IF(WEEKDAY(F5,2)>5,1,0) -> 0 | P5: =IF(K5>Parameters!$B$17,1,0) -> 0 | Q5: =IF(AND(F5<=Parameters!$B$6,F5>Parameters!$B$6-Parameters!$B$18),1,0) -> 0 | R5: =IF(COUNTIF(Parameters!$A$51:$A$58,H5)=0,1,0) -> 0 | S5: =IF(AND(I5="Manual",L5>0),1,0) -> 0 | T5: =IF(AND(C5>=Parameters!$B$22,ROUND(MOD(ROUND(C5,2),Parameters!$B$21),2)=0),1,0) -> 0 | U5: =IF(LEN(TRIM(J5))=0,1,0) -> 0 | V5: =IF(AND(I5="Manual",C5<Parameters!$B$19,C5>=Parameters!$B$19*(1-Parameters!$B$20)),1,0) -> 0 | W5: =IF(AND(I5="Manual",M5>0),1,0) -> 0 | X5: =0 -> 0 | Y5: =N5*Parameters!$B$38+O5*Parameters!$B$39+P5*Parameters!$B$40+Q5*Parameters!$B$41+R5*Parameters!$B$42+S5*Parameters!$B$43+T5*Parameters!$B$44+U5*Parameters!$B$45+V5*Parameters!$B$46+W5*Parameters!$B$47+X5*Parameters!$B$48 -> 0 | Z5: =IF(Y5>=Parameters!$B$25,"High","")
A6: 1002 | B6: =COUNTIF(JE_Lines!$B$5:$B$1733,A6) -> 2 | C6: =SUMIFS(JE_Lines!$G$5:$G$1733,JE_Lines!$B$5:$B$1733,A6) -> 2895.32 | D6: =SUMIFS(JE_Lines!$H$5:$H$1733,JE_Lines!$B$5:$B$1733,A6) -> 2895.32 | E6: =C6-D6 -> 0 | F6: =INDEX(JE_Lines!$C$5:$C$1733,MATCH(A6,JE_Lines!$B$5:$B$1733,0)) -> 45658 | G6: =INDEX(JE_Lines!$D$5:$D$1733,MATCH(A6,JE_Lines!$B$5:$B$1733,0)) -> 45656 | H6: =INDEX(JE_Lines!$I$5:$I$1733,MATCH(A6,JE_Lines!$B$5:$B$1733,0)) -> SYS_AR | I6: =INDEX(JE_Lines!$J$5:$J$1733,MATCH(A6,JE_Lines!$B$5:$B$1733,0)) -> System | J6: =IF(LEN(INDEX(JE_Lines!$K$5:$K$1733,MATCH(A6,JE_Lines!$B$5:$B$1733,0)))=0,"",INDEX(JE_Lines!$K$5:$K$1733,MATCH(A6,JE_Lines!$B$5:$B$1733,0))) -> Sales invoice batch | K6: =F6-G6 -> 2 | L6: =COUNTIFS(JE_Lines!$B$5:$B$1733,A6,JE_Lines!$F$5:$F$1733,"Revenue") -> 1 | M6: =COUNTIFS(JE_Lines!$B$5:$B$1733,A6,JE_Lines!$F$5:$F$1733,"Suspense") -> 0 | N6: =IF(ABS(E6)>Parameters!$B$23,1,0) -> 0 | O6: =IF(WEEKDAY(F6,2)>5,1,0) -> 0 | P6: =IF(K6>Parameters!$B$17,1,0) -> 0 | Q6: =IF(AND(F6<=Parameters!$B$6,F6>Parameters!$B$6-Parameters!$B$18),1,0) -> 0 | R6: =IF(COUNTIF(Parameters!$A$51:$A$58,H6)=0,1,0) -> 0 | S6: =IF(AND(I6="Manual",L6>0),1,0) -> 0 | T6: =IF(AND(C6>=Parameters!$B$22,ROUND(MOD(ROUND(C6,2),Parameters!$B$21),2)=0),1,0) -> 0 | U6: =IF(LEN(TRIM(J6))=0,1,0) -> 0 | V6: =IF(AND(I6="Manual",C6<Parameters!$B$19,C6>=Parameters!$B$19*(1-Parameters!$B$20)),1,0) -> 0 | W6: =IF(AND(I6="Manual",M6>0),1,0) -> 0 | X6: =IF(A6-A5>1,1,0) -> 0 | Y6: =N6*Parameters!$B$38+O6*Parameters!$B$39+P6*Parameters!$B$40+Q6*Parameters!$B$41+R6*Parameters!$B$42+S6*Parameters!$B$43+T6*Parameters!$B$44+U6*Parameters!$B$45+V6*Parameters!$B$46+W6*Parameters!$B$47+X6*Parameters!$B$48 -> 0 | Z6: =IF(Y6>=Parameters!$B$25,"High","")
A7: 1003 | B7: =COUNTIF(JE_Lines!$B$5:$B$1733,A7) -> 3 | C7: =SUMIFS(JE_Lines!$G$5:$G$1733,JE_Lines!$B$5:$B$1733,A7) -> 14023.69 | D7: =SUMIFS(JE_Lines!$H$5:$H$1733,JE_Lines!$B$5:$B$1733,A7) -> 14023.69 | E7: =C7-D7 -> 0 | F7: =INDEX(JE_Lines!$C$5:$C$1733,MATCH(A7,JE_Lines!$B$5:$B$1733,0)) -> 45658 | G7: =INDEX(JE_Lines!$D$5:$D$1733,MATCH(A7,JE_Lines!$B$5:$B$1733,0)) -> 45655 | H7: =INDEX(JE_Lines!$I$5:$I$1733,MATCH(A7,JE_Lines!$B$5:$B$1733,0)) -> SYS_AR | I7: =INDEX(JE_Lines!$J$5:$J$1733,MATCH(A7,JE_Lines!$B$5:$B$1733,0)) -> System | J7: =IF(LEN(INDEX(JE_Lines!$K$5:$K$1733,MATCH(A7,JE_Lines!$B$5:$B$1733,0)))=0,"",INDEX(JE_Lines!$K$5:$K$1733,MATCH(A7,JE_Lines!$B$5:$B$1733,0))) -> Sales invoice batch | K7: =F7-G7 -> 3 | L7: =COUNTIFS(JE_Lines!$B$5:$B$1733,A7,JE_Lines!$F$5:$F$1733,"Revenue") -> 1 | M7: =COUNTIFS(JE_Lines!$B$5:$B$1733,A7,JE_Lines!$F$5:$F$1733,"Suspense") -> 0 | N7: =IF(ABS(E7)>Parameters!$B$23,1,0) -> 0 | O7: =IF(WEEKDAY(F7,2)>5,1,0) -> 0 | P7: =IF(K7>Parameters!$B$17,1,0) -> 0 | Q7: =IF(AND(F7<=Parameters!$B$6,F7>Parameters!$B$6-Parameters!$B$18),1,0) -> 0 | R7: =IF(COUNTIF(Parameters!$A$51:$A$58,H7)=0,1,0) -> 0 | S7: =IF(AND(I7="Manual",L7>0),1,0) -> 0 | T7: =IF(AND(C7>=Parameters!$B$22,ROUND(MOD(ROUND(C7,2),Parameters!$B$21),2)=0),1,0) -> 0 | U7: =IF(LEN(TRIM(J7))=0,1,0) -> 0 | V7: =IF(AND(I7="Manual",C7<Parameters!$B$19,C7>=Parameters!$B$19*(1-Parameters!$B$20)),1,0) -> 0 | W7: =IF(AND(I7="Manual",M7>0),1,0) -> 0 | X7: =IF(A7-A6>1,1,0) -> 0 | Y7: =N7*Parameters!$B$38+O7*Parameters!$B$39+P7*Parameters!$B$40+Q7*Parameters!$B$41+R7*Parameters!$B$42+S7*Parameters!$B$43+T7*Parameters!$B$44+U7*Parameters!$B$45+V7*Parameters!$B$46+W7*Parameters!$B$47+X7*Parameters!$B$48 -> 0 | Z7: =IF(Y7>=Parameters!$B$25,"High","")
A8: 1004 | B8: =COUNTIF(JE_Lines!$B$5:$B$1733,A8) -> 2 | C8: =SUMIFS(JE_Lines!$G$5:$G$1733,JE_Lines!$B$5:$B$1733,A8) -> 1008.74 | D8: =SUMIFS(JE_Lines!$H$5:$H$1733,JE_Lines!$B$5:$B$1733,A8) -> 1008.74 | E8: =C8-D8 -> 0 | F8: =INDEX(JE_Lines!$C$5:$C$1733,MATCH(A8,JE_Lines!$B$5:$B$1733,0)) -> 45659 | G8: =INDEX(JE_Lines!$D$5:$D$1733,MATCH(A8,JE_Lines!$B$5:$B$1733,0)) -> 45657 | H8: =INDEX(JE_Lines!$I$5:$I$1733,MATCH(A8,JE_Lines!$B$5:$B$1733,0)) -> SYS_AR | I8: =INDEX(JE_Lines!$J$5:$J$1733,MATCH(A8,JE_Lines!$B$5:$B$1733,0)) -> System | J8: =IF(LEN(INDEX(JE_Lines!$K$5:$K$1733,MATCH(A8,JE_Lines!$B$5:$B$1733,0)))=0,"",INDEX(JE_Lines!$K$5:$K$1733,MATCH(A8,JE_Lines!$B$5:$B$1733,0))) -> Sales invoice batch | K8: =F8-G8 -> 2 | L8: =COUNTIFS(JE_Lines!$B$5:$B$1733,A8,JE_Lines!$F$5:$F$1733,"Revenue") -> 1 | M8: =COUNTIFS(JE_Lines!$B$5:$B$1733,A8,JE_Lines!$F$5:$F$1733,"Suspense") -> 0 | N8: =IF(ABS(E8)>Parameters!$B$23,1,0) -> 0 | O8: =IF(WEEKDAY(F8,2)>5,1,0) -> 0 | P8: =IF(K8>Parameters!$B$17,1,0) -> 0 | Q8: =IF(AND(F8<=Parameters!$B$6,F8>Parameters!$B$6-Parameters!$B$18),1,0) -> 0 | R8: =IF(COUNTIF(Parameters!$A$51:$A$58,H8)=0,1,0) -> 0 | S8: =IF(AND(I8="Manual",L8>0),1,0) -> 0 | T8: =IF(AND(C8>=Parameters!$B$22,ROUND(MOD(ROUND(C8,2),Parameters!$B$21),2)=0),1,0) -> 0 | U8: =IF(LEN(TRIM(J8))=0,1,0) -> 0 | V8: =IF(AND(I8="Manual",C8<Parameters!$B$19,C8>=Parameters!$B$19*(1-Parameters!$B$20)),1,0) -> 0 | W8: =IF(AND(I8="Manual",M8>0),1,0) -> 0 | X8: =IF(A8-A7>1,1,0) -> 0 | Y8: =N8*Parameters!$B$38+O8*Parameters!$B$39+P8*Parameters!$B$40+Q8*Parameters!$B$41+R8*Parameters!$B$42+S8*Parameters!$B$43+T8*Parameters!$B$44+U8*Parameters!$B$45+V8*Parameters!$B$46+W8*Parameters!$B$47+X8*Parameters!$B$48 -> 0 | Z8: =IF(Y8>=Parameters!$B$25,"High","")
A9: 1005 | B9: =COUNTIF(JE_Lines!$B$5:$B$1733,A9) -> 2 | C9: =SUMIFS(JE_Lines!$G$5:$G$1733,JE_Lines!$B$5:$B$1733,A9) -> 233.11 | D9: =SUMIFS(JE_Lines!$H$5:$H$1733,JE_Lines!$B$5:$B$1733,A9) -> 233.11 | E9: =C9-D9 -> 0 | F9: =INDEX(JE_Lines!$C$5:$C$1733,MATCH(A9,JE_Lines!$B$5:$B$1733,0)) -> 45659 | G9: =INDEX(JE_Lines!$D$5:$D$1733,MATCH(A9,JE_Lines!$B$5:$B$1733,0)) -> 45656 | H9: =INDEX(JE_Lines!$I$5:$I$1733,MATCH(A9,JE_Lines!$B$5:$B$1733,0)) -> FIN02 | I9: =INDEX(JE_Lines!$J$5:$J$1733,MATCH(A9,JE_Lines!$B$5:$B$1733,0)) -> Manual | J9: =IF(LEN(INDEX(JE_Lines!$K$5:$K$1733,MATCH(A9,JE_Lines!$B$5:$B$1733,0)))=0,"",INDEX(JE_Lines!$K$5:$K$1733,MATCH(A9,JE_Lines!$B$5:$B$1733,0))) -> Accrual for sundry costs | K9: =F9-G9 -> 3 | L9: =COUNTIFS(JE_Lines!$B$5:$B$1733,A9,JE_Lines!$F$5:$F$1733,"Revenue") -> 0 | M9: =COUNTIFS(JE_Lines!$B$5:$B$1733,A9,JE_Lines!$F$5:$F$1733,"Suspense") -> 0 | N9: =IF(ABS(E9)>Parameters!$B$23,1,0) -> 0 | O9: =IF(WEEKDAY(F9,2)>5,1,0) -> 0 | P9: =IF(K9>Parameters!$B$17,1,0) -> 0 | Q9: =IF(AND(F9<=Parameters!$B$6,F9>Parameters!$B$6-Parameters!$B$18),1,0) -> 0 | R9: =IF(COUNTIF(Parameters!$A$51:$A$58,H9)=0,1,0) -> 0 | S9: =IF(AND(I9="Manual",L9>0),1,0) -> 0 | T9: =IF(AND(C9>=Parameters!$B$22,ROUND(MOD(ROUND(C9,2),Parameters!$B$21),2)=0),1,0) -> 0 | U9: =IF(LEN(TRIM(J9))=0,1,0) -> 0 | V9: =IF(AND(I9="Manual",C9<Parameters!$B$19,C9>=Parameters!$B$19*(1-Parameters!$B$20)),1,0) -> 0 | W9: =IF(AND(I9="Manual",M9>0),1,0) -> 0 | X9: =IF(A9-A8>1,1,0) -> 0 | Y9: =N9*Parameters!$B$38+O9*Parameters!$B$39+P9*Parameters!$B$40+Q9*Parameters!$B$41+R9*Parameters!$B$42+S9*Parameters!$B$43+T9*Parameters!$B$44+U9*Parameters!$B$45+V9*Parameters!$B$46+W9*Parameters!$B$47+X9*Parameters!$B$48 -> 0 | Z9: =IF(Y9>=Parameters!$B$25,"High","")
A10: 1006 | B10: =COUNTIF(JE_Lines!$B$5:$B$1733,A10) -> 2 | C10: =SUMIFS(JE_Lines!$G$5:$G$1733,JE_Lines!$B$5:$B$1733,A10) -> 37000 | D10: =SUMIFS(JE_Lines!$H$5:$H$1733,JE_Lines!$B$5:$B$1733,A10) -> 37000 | E10: =C10-D10 -> 0 | F10: =INDEX(JE_Lines!$C$5:$C$1733,MATCH(A10,JE_Lines!$B$5:$B$1733,0)) -> 45659 | G10: =INDEX(JE_Lines!$D$5:$D$1733,MATCH(A10,JE_Lines!$B$5:$B$1733,0)) -> 45659 | H10: =INDEX(JE_Lines!$I$5:$I$1733,MATCH(A10,JE_Lines!$B$5:$B$1733,0)) -> FIN01 | I10: =INDEX(JE_Lines!$J$5:$J$1733,MATCH(A10,JE_Lines!$B$5:$B$1733,0)) -> Manual | J10: =IF(LEN(INDEX(JE_Lines!$K$5:$K$1733,MATCH(A10,JE_Lines!$B$5:$B$1733,0)))=0,"",INDEX(JE_Lines!$K$5:$K$1733,MATCH(A10,JE_Lines!$B$5:$B$1733,0))) -> Round accrual 3 | K10: =F10-G10 -> 0 | L10: =COUNTIFS(JE_Lines!$B$5:$B$1733,A10,JE_Lines!$F$5:$F$1733,"Revenue") -> 0 | M10: =COUNTIFS(JE_Lines!$B$5:$B$1733,A10,JE_Lines!$F$5:$F$1733,"Suspense") -> 0 | N10: =IF(ABS(E10)>Parameters!$B$23,1,0) -> 0 | O10: =IF(WEEKDAY(F10,2)>5,1,0) -> 0 | P10: =IF(K10>Parameters!$B$17,1,0) -> 0 | Q10: =IF(AND(F10<=Parameters!$B$6,F10>Parameters!$B$6-Parameters!$B$18),1,0) -> 0 | R10: =IF(COUNTIF(Parameters!$A$51:$A$58,H10)=0,1,0) -> 0 | S10: =IF(AND(I10="Manual",L10>0),1,0) -> 0 | T10: =IF(AND(C10>=Parameters!$B$22,ROUND(MOD(ROUND(C10,2),Parameters!$B$21),2)=0),1,0) -> 1 | U10: =IF(LEN(TRIM(J10))=0,1,0) -> 0 | V10: =IF(AND(I10="Manual",C10<Parameters!$B$19,C10>=Parameters!$B$19*(1-Parameters!$B$20)),1,0) -> 0 | W10: =IF(AND(I10="Manual",M10>0),1,0) -> 0 | X10: =IF(A10-A9>1,1,0) -> 0 | Y10: =N10*Parameters!$B$38+O10*Parameters!$B$39+P10*Parameters!$B$40+Q10*Parameters!$B$41+R10*Parameters!$B$42+S10*Parameters!$B$43+T10*Parameters!$B$44+U10*Parameters!$B$45+V10*Parameters!$B$46+W10*Parameters!$B$47+X10*Parameters!$B$48 -> 2 | Z10: =IF(Y10>=Parameters!$B$25,"High","")
A11: 1007 | B11: =COUNTIF(JE_Lines!$B$5:$B$1733,A11) -> 3 | C11: =SUMIFS(JE_Lines!$G$5:$G$1733,JE_Lines!$B$5:$B$1733,A11) -> 12742.41 | D11: =SUMIFS(JE_Lines!$H$5:$H$1733,JE_Lines!$B$5:$B$1733,A11) -> 12742.41 | E11: =C11-D11 -> 0 | F11: =INDEX(JE_Lines!$C$5:$C$1733,MATCH(A11,JE_Lines!$B$5:$B$1733,0)) -> 45660 | G11: =INDEX(JE_Lines!$D$5:$D$1733,MATCH(A11,JE_Lines!$B$5:$B$1733,0)) -> 45657 | H11: =INDEX(JE_Lines!$I$5:$I$1733,MATCH(A11,JE_Lines!$B$5:$B$1733,0)) -> SYS_AP | I11: =INDEX(JE_Lines!$J$5:$J$1733,MATCH(A11,JE_Lines!$B$5:$B$1733,0)) -> System | J11: =IF(LEN(INDEX(JE_Lines!$K$5:$K$1733,MATCH(A11,JE_Lines!$B$5:$B$1733,0)))=0,"",INDEX(JE_Lines!$K$5:$K$1733,MATCH(A11,JE_Lines!$B$5:$B$1733,0))) -> Supplier invoices | K11: =F11-G11 -> 3 | L11: =COUNTIFS(JE_Lines!$B$5:$B$1733,A11,JE_Lines!$F$5:$F$1733,"Revenue") -> 0 | M11: =COUNTIFS(JE_Lines!$B$5:$B$1733,A11,JE_Lines!$F$5:$F$1733,"Suspense") -> 0 | N11: =IF(ABS(E11)>Parameters!$B$23,1,0) -> 0 | O11: =IF(WEEKDAY(F11,2)>5,1,0) -> 0 | P11: =IF(K11>Parameters!$B$17,1,0) -> 0 | Q11: =IF(AND(F11<=Parameters!$B$6,F11>Parameters!$B$6-Parameters!$B$18),1,0) -> 0 | R11: =IF(COUNTIF(Parameters!$A$51:$A$58,H11)=0,1,0) -> 0 | S11: =IF(AND(I11="Manual",L11>0),1,0) -> 0 | T11: =IF(AND(C11>=Parameters!$B$22,ROUND(MOD(ROUND(C11,2),Parameters!$B$21),2)=0),1,0) -> 0 | U11: =IF(LEN(TRIM(J11))=0,1,0) -> 0 | V11: =IF(AND(I11="Manual",C11<Parameters!$B$19,C11>=Parameters!$B$19*(1-Parameters!$B$20)),1,0) -> 0 | W11: =IF(AND(I11="Manual",M11>0),1,0) -> 0 | X11: =IF(A11-A10>1,1,0) -> 0 | Y11: =N11*Parameters!$B$38+O11*Parameters!$B$39+P11*Parameters!$B$40+Q11*Parameters!$B$41+R11*Parameters!$B$42+S11*Parameters!$B$43+T11*Parameters!$B$44+U11*Parameters!$B$45+V11*Parameters!$B$46+W11*Parameters!$B$47+X11*Parameters!$B$48 -> 0 | Z11: =IF(Y11>=Parameters!$B$25,"High","")
A12: 1008 | B12: =COUNTIF(JE_Lines!$B$5:$B$1733,A12) -> 3 | C12: =SUMIFS(JE_Lines!$G$5:$G$1733,JE_Lines!$B$5:$B$1733,A12) -> 115525.82 | D12: =SUMIFS(JE_Lines!$H$5:$H$1733,JE_Lines!$B$5:$B$1733,A12) -> 115525.82 | E12: =C12-D12 -> 0 | F12: =INDEX(JE_Lines!$C$5:$C$1733,MATCH(A12,JE_Lines!$B$5:$B$1733,0)) -> 45660 | G12: =INDEX(JE_Lines!$D$5:$D$1733,MATCH(A12,JE_Lines!$B$5:$B$1733,0)) -> 45658 | H12: =INDEX(JE_Lines!$I$5:$I$1733,MATCH(A12,JE_Lines!$B$5:$B$1733,0)) -> SYS_PAY | I12: =INDEX(JE_Lines!$J$5:$J$1733,MATCH(A12,JE_Lines!$B$5:$B$1733,0)) -> System | J12: =IF(LEN(INDEX(JE_Lines!$K$5:$K$1733,MATCH(A12,JE_Lines!$B$5:$B$1733,0)))=0,"",INDEX(JE_Lines!$K$5:$K$1733,MATCH(A12,JE_Lines!$B$5:$B$1733,0))) -> Supplier payments | K12: =F12-G12 -> 2 | L12: =COUNTIFS(JE_Lines!$B$5:$B$1733,A12,JE_Lines!$F$5:$F$1733,"Revenue") -> 0 | M12: =COUNTIFS(JE_Lines!$B$5:$B$1733,A12,JE_Lines!$F$5:$F$1733,"Suspense") -> 0 | N12: =IF(ABS(E12)>Parameters!$B$23,1,0) -> 0 | O12: =IF(WEEKDAY(F12,2)>5,1,0) -> 0 | P12: =IF(K12>Parameters!$B$17,1,0) -> 0 | Q12: =IF(AND(F12<=Parameters!$B$6,F12>Parameters!$B$6-Parameters!$B$18),1,0) -> 0 | R12: =IF(COUNTIF(Parameters!$A$51:$A$58,H12)=0,1,0) -> 0 | S12: =IF(AND(I12="Manual",L12>0),1,0) -> 0 | T12: =IF(AND(C12>=Parameters!$B$22,ROUND(MOD(ROUND(C12,2),Parameters!$B$21),2)=0),1,0) -> 0 | U12: =IF(LEN(TRIM(J12))=0,1,0) -> 0 | V12: =IF(AND(I12="Manual",C12<Parameters!$B$19,C12>=Parameters!$B$19*(1-Parameters!$B$20)),1,0) -> 0 | W12: =IF(AND(I12="Manual",M12>0),1,0) -> 0 | X12: =IF(A12-A11>1,1,0) -> 0 | Y12: =N12*Parameters!$B$38+O12*Parameters!$B$39+P12*Parameters!$B$40+Q12*Parameters!$B$41+R12*Parameters!$B$42+S12*Parameters!$B$43+T12*Parameters!$B$44+U12*Parameters!$B$45+V12*Parameters!$B$46+W12*Parameters!$B$47+X12*Parameters!$B$48 -> 0 | Z12: =IF(Y12>=Parameters!$B$25,"High","")
A13: 1009 | B13: =COUNTIF(JE_Lines!$B$5:$B$1733,A13) -> 3 | C13: =SUMIFS(JE_Lines!$G$5:$G$1733,JE_Lines!$B$5:$B$1733,A13) -> 2509.81 | D13: =SUMIFS(JE_Lines!$H$5:$H$1733,JE_Lines!$B$5:$B$1733,A13) -> 2509.81 | E13: =C13-D13 -> 0 | F13: =INDEX(JE_Lines!$C$5:$C$1733,MATCH(A13,JE_Lines!$B$5:$B$1733,0)) -> 45663 | G13: =INDEX(JE_Lines!$D$5:$D$1733,MATCH(A13,JE_Lines!$B$5:$B$1733,0)) -> 45661 | H13: =INDEX(JE_Lines!$I$5:$I$1733,MATCH(A13,JE_Lines!$B$5:$B$1733,0)) -> SYS_PAY | I13: =INDEX(JE_Lines!$J$5:$J$1733,MATCH(A13,JE_Lines!$B$5:$B$1733,0)) -> System | J13: =IF(LEN(INDEX(JE_Lines!$K$5:$K$1733,MATCH(A13,JE_Lines!$B$5:$B$1733,0)))=0,"",INDEX(JE_Lines!$K$5:$K$1733,MATCH(A13,JE_Lines!$B$5:$B$1733,0))) -> Supplier payments | K13: =F13-G13 -> 2 | L13: =COUNTIFS(JE_Lines!$B$5:$B$1733,A13,JE_Lines!$F$5:$F$1733,"Revenue") -> 0 | M13: =COUNTIFS(JE_Lines!$B$5:$B$1733,A13,JE_Lines!$F$5:$F$1733,"Suspense") -> 0 | N13: =IF(ABS(E13)>Parameters!$B$23,1,0) -> 0 | O13: =IF(WEEKDAY(F13,2)>5,1,0) -> 0 | P13: =IF(K13>Parameters!$B$17,1,0) -> 0 | Q13: =IF(AND(F13<=Parameters!$B$6,F13>Parameters!$B$6-Parameters!$B$18),1,0) -> 0 | R13: =IF(COUNTIF(Parameters!$A$51:$A$58,H13)=0,1,0) -> 0 | S13: =IF(AND(I13="Manual",L13>0),1,0) -> 0 | T13: =IF(AND(C13>=Parameters!$B$22,ROUND(MOD(ROUND(C13,2),Parameters!$B$21),2)=0),1,0) -> 0 | U13: =IF(LEN(TRIM(J13))=0,1,0) -> 0 | V13: =IF(AND(I13="Manual",C13<Parameters!$B$19,C13>=Parameters!$B$19*(1-Parameters!$B$20)),1,0) -> 0 | W13: =IF(AND(I13="Manual",M13>0),1,0) -> 0 | X13: =IF(A13-A12>1,1,0) -> 0 | Y13: =N13*Parameters!$B$38+O13*Parameters!$B$39+P13*Parameters!$B$40+Q13*Parameters!$B$41+R13*Parameters!$B$42+S13*Parameters!$B$43+T13*Parameters!$B$44+U13*Parameters!$B$45+V13*Parameters!$B$46+W13*Parameters!$B$47+X13*Parameters!$B$48 -> 0 | Z13: =IF(Y13>=Parameters!$B$25,"High","")
A14: 1010 | B14: =COUNTIF(JE_Lines!$B$5:$B$1733,A14) -> 2 | C14: =SUMIFS(JE_Lines!$G$5:$G$1733,JE_Lines!$B$5:$B$1733,A14) -> 20143 | D14: =SUMIFS(JE_Lines!$H$5:$H$1733,JE_Lines!$B$5:$B$1733,A14) -> 20143 | E14: =C14-D14 -> 0 | F14: =INDEX(JE_Lines!$C$5:$C$1733,MATCH(A14,JE_Lines!$B$5:$B$1733,0)) -> 45663 | G14: =INDEX(JE_Lines!$D$5:$D$1733,MATCH(A14,JE_Lines!$B$5:$B$1733,0)) -> 45663 | H14: =INDEX(JE_Lines!$I$5:$I$1733,MATCH(A14,JE_Lines!$B$5:$B$1733,0)) -> SYS_AP | I14: =INDEX(JE_Lines!$J$5:$J$1733,MATCH(A14,JE_Lines!$B$5:$B$1733,0)) -> System | J14: =IF(LEN(INDEX(JE_Lines!$K$5:$K$1733,MATCH(A14,JE_Lines!$B$5:$B$1733,0)))=0,"",INDEX(JE_Lines!$K$5:$K$1733,MATCH(A14,JE_Lines!$B$5:$B$1733,0))) -> Supplier invoices | K14: =F14-G14 -> 0 | L14: =COUNTIFS(JE_Lines!$B$5:$B$1733,A14,JE_Lines!$F$5:$F$1733,"Revenue") -> 0 | M14: =COUNTIFS(JE_Lines!$B$5:$B$1733,A14,JE_Lines!$F$5:$F$1733,"Suspense") -> 0 | N14: =IF(ABS(E14)>Parameters!$B$23,1,0) -> 0 | O14: =IF(WEEKDAY(F14,2)>5,1,0) -> 0 | P14: =IF(K14>Parameters!$B$17,1,0) -> 0 | Q14: =IF(AND(F14<=Parameters!$B$6,F14>Parameters!$B$6-Parameters!$B$18),1,0) -> 0 | R14: =IF(COUNTIF(Parameters!$A$51:$A$58,H14)=0,1,0) -> 0 | S14: =IF(AND(I14="Manual",L14>0),1,0) -> 0 | T14: =IF(AND(C14>=Parameters!$B$22,ROUND(MOD(ROUND(C14,2),Parameters!$B$21),2)=0),1,0) -> 0 | U14: =IF(LEN(TRIM(J14))=0,1,0) -> 0 | V14: =IF(AND(I14="Manual",C14<Parameters!$B$19,C14>=Parameters!$B$19*(1-Parameters!$B$20)),1,0) -> 0 | W14: =IF(AND(I14="Manual",M14>0),1,0) -> 0 | X14: =IF(A14-A13>1,1,0) -> 0 | Y14: =N14*Parameters!$B$38+O14*Parameters!$B$39+P14*Parameters!$B$40+Q14*Parameters!$B$41+R14*Parameters!$B$42+S14*Parameters!$B$43+T14*Parameters!$B$44+U14*Parameters!$B$45+V14*Parameters!$B$46+W14*Parameters!$B$47+X14*Parameters!$B$48 -> 0 | Z14: =IF(Y14>=Parameters!$B$25,"High","")
A15: 1011 | B15: =COUNTIF(JE_Lines!$B$5:$B$1733,A15) -> 2 | C15: =SUMIFS(JE_Lines!$G$5:$G$1733,JE_Lines!$B$5:$B$1733,A15) -> 107970.06 | D15: =SUMIFS(JE_Lines!$H$5:$H$1733,JE_Lines!$B$5:$B$1733,A15) -> 107970.06 | E15: =C15-D15 -> 0 | F15: =INDEX(JE_Lines!$C$5:$C$1733,MATCH(A15,JE_Lines!$B$5:$B$1733,0)) -> 45664 | G15: =INDEX(JE_Lines!$D$5:$D$1733,MATCH(A15,JE_Lines!$B$5:$B$1733,0)) -> 45664 | H15: =INDEX(JE_Lines!$I$5:$I$1733,MATCH(A15,JE_Lines!$B$5:$B$1733,0)) -> SYS_PAY | I15: =INDEX(JE_Lines!$J$5:$J$1733,MATCH(A15,JE_Lines!$B$5:$B$1733,0)) -> System | J15: =IF(LEN(INDEX(JE_Lines!$K$5:$K$1733,MATCH(A15,JE_Lines!$B$5:$B$1733,0)))=0,"",INDEX(JE_Lines!$K$5:$K$1733,MATCH(A15,JE_Lines!$B$5:$B$1733,0))) -> Supplier payments | K15: =F15-G15 -> 0 | L15: =COUNTIFS(JE_Lines!$B$5:$B$1733,A15,JE_Lines!$F$5:$F$1733,"Revenue") -> 0 | M15: =COUNTIFS(JE_Lines!$B$5:$B$1733,A15,JE_Lines!$F$5:$F$1733,"Suspense") -> 0 | N15: =IF(ABS(E15)>Parameters!$B$23,1,0) -> 0 | O15: =IF(WEEKDAY(F15,2)>5,1,0) -> 0 | P15: =IF(K15>Parameters!$B$17,1,0) -> 0 | Q15: =IF(AND(F15<=Parameters!$B$6,F15>Parameters!$B$6-Parameters!$B$18),1,0) -> 0 | R15: =IF(COUNTIF(Parameters!$A$51:$A$58,H15)=0,1,0) -> 0 | S15: =IF(AND(I15="Manual",L15>0),1,0) -> 0 | T15: =IF(AND(C15>=Parameters!$B$22,ROUND(MOD(ROUND(C15,2),Parameters!$B$21),2)=0),1,0) -> 0 | U15: =IF(LEN(TRIM(J15))=0,1,0) -> 0 | V15: =IF(AND(I15="Manual",C15<Parameters!$B$19,C15>=Parameters!$B$19*(1-Parameters!$B$20)),1,0) -> 0 | W15: =IF(AND(I15="Manual",M15>0),1,0) -> 0 | X15: =IF(A15-A14>1,1,0) -> 0 | Y15: =N15*Parameters!$B$38+O15*Parameters!$B$39+P15*Parameters!$B$40+Q15*Parameters!$B$41+R15*Parameters!$B$42+S15*Parameters!$B$43+T15*Parameters!$B$44+U15*Parameters!$B$45+V15*Parameters!$B$46+W15*Parameters!$B$47+X15*Parameters!$B$48 -> 0 | Z15: =IF(Y15>=Parameters!$B$25,"High","")
A16: 1012 | B16: =COUNTIF(JE_Lines!$B$5:$B$1733,A16) -> 2 | C16: =SUMIFS(JE_Lines!$G$5:$G$1733,JE_Lines!$B$5:$B$1733,A16) -> 662.96 | D16: =SUMIFS(JE_Lines!$H$5:$H$1733,JE_Lines!$B$5:$B$1733,A16) -> 662.96 | E16: =C16-D16 -> 0 | F16: =INDEX(JE_Lines!$C$5:$C$1733,MATCH(A16,JE_Lines!$B$5:$B$1733,0)) -> 45664 | G16: =INDEX(JE_Lines!$D$5:$D$1733,MATCH(A16,JE_Lines!$B$5:$B$1733,0)) -> 45663 | H16: =INDEX(JE_Lines!$I$5:$I$1733,MATCH(A16,JE_Lines!$B$5:$B$1733,0)) -> SYS_AR | I16: =INDEX(JE_Lines!$J$5:$J$1733,MATCH(A16,JE_Lines!$B$5:$B$1733,0)) -> System | J16: =IF(LEN(INDEX(JE_Lines!$K$5:$K$1733,MATCH(A16,JE_Lines!$B$5:$B$1733,0)))=0,"",INDEX(JE_Lines!$K$5:$K$1733,MATCH(A16,JE_Lines!$B$5:$B$1733,0))) -> Cost of sales posting | K16: =F16-G16 -> 1 | L16: =COUNTIFS(JE_Lines!$B$5:$B$1733,A16,JE_Lines!$F$5:$F$1733,"Revenue") -> 0 | M16: =COUNTIFS(JE_Lines!$B$5:$B$1733,A16,JE_Lines!$F$5:$F$1733,"Suspense") -> 0 | N16: =IF(ABS(E16)>Parameters!$B$23,1,0) -> 0 | O16: =IF(WEEKDAY(F16,2)>5,1,0) -> 0 | P16: =IF(K16>Parameters!$B$17,1,0) -> 0 | Q16: =IF(AND(F16<=Parameters!$B$6,F16>Parameters!$B$6-Parameters!$B$18),1,0) -> 0 | R16: =IF(COUNTIF(Parameters!$A$51:$A$58,H16)=0,1,0) -> 0 | S16: =IF(AND(I16="Manual",L16>0),1,0) -> 0 | T16: =IF(AND(C16>=Parameters!$B$22,ROUND(MOD(ROUND(C16,2),Parameters!$B$21),2)=0),1,0) -> 0 | U16: =IF(LEN(TRIM(J16))=0,1,0) -> 0 | V16: =IF(AND(I16="Manual",C16<Parameters!$B$19,C16>=Parameters!$B$19*(1-Parameters!$B$20)),1,0) -> 0 | W16: =IF(AND(I16="Manual",M16>0),1,0) -> 0 | X16: =IF(A16-A15>1,1,0) -> 0 | Y16: =N16*Parameters!$B$38+O16*Parameters!$B$39+P16*Parameters!$B$40+Q16*Parameters!$B$41+R16*Parameters!$B$42+S16*Parameters!$B$43+T16*Parameters!$B$44+U16*Parameters!$B$45+V16*Parameters!$B$46+W16*Parameters!$B$47+X16*Parameters!$B$48 -> 0 | Z16: =IF(Y16>=Parameters!$B$25,"High","")
A17: 1013 | B17: =COUNTIF(JE_Lines!$B$5:$B$1733,A17) -> 2 | C17: =SUMIFS(JE_Lines!$G$5:$G$1733,JE_Lines!$B$5:$B$1733,A17) -> 777.69 | D17: =SUMIFS(JE_Lines!$H$5:$H$1733,JE_Lines!$B$5:$B$1733,A17) -> 777.69 | E17: =C17-D17 -> 0 | F17: =INDEX(JE_Lines!$C$5:$C$1733,MATCH(A17,JE_Lines!$B$5:$B$1733,0)) -> 45664 | G17: =INDEX(JE_Lines!$D$5:$D$1733,MATCH(A17,JE_Lines!$B$5:$B$1733,0)) -> 45662 | H17: =INDEX(JE_Lines!$I$5:$I$1733,MATCH(A17,JE_Lines!$B$5:$B$1733,0)) -> SYS_AP | I17: =INDEX(JE_Lines!$J$5:$J$1733,MATCH(A17,JE_Lines!$B$5:$B$1733,0)) -> System | J17: =IF(LEN(INDEX(JE_Lines!$K$5:$K$1733,MATCH(A17,JE_Lines!$B$5:$B$1733,0)))=0,"",INDEX(JE_Lines!$K$5:$K$1733,MATCH(A17,JE_Lines!$B$5:$B$1733,0))) -> Supplier invoices | K17: =F17-G17 -> 2 | L17: =COUNTIFS(JE_Lines!$B$5:$B$1733,A17,JE_Lines!$F$5:$F$1733,"Revenue") -> 0 | M17: =COUNTIFS(JE_Lines!$B$5:$B$1733,A17,JE_Lines!$F$5:$F$1733,"Suspense") -> 0 | N17: =IF(ABS(E17)>Parameters!$B$23,1,0) -> 0 | O17: =IF(WEEKDAY(F17,2)>5,1,0) -> 0 | P17: =IF(K17>Parameters!$B$17,1,0) -> 0 | Q17: =IF(AND(F17<=Parameters!$B$6,F17>Parameters!$B$6-Parameters!$B$18),1,0) -> 0 | R17: =IF(COUNTIF(Parameters!$A$51:$A$58,H17)=0,1,0) -> 0 | S17: =IF(AND(I17="Manual",L17>0),1,0) -> 0 | T17: =IF(AND(C17>=Parameters!$B$22,ROUND(MOD(ROUND(C17,2),Parameters!$B$21),2)=0),1,0) -> 0 | U17: =IF(LEN(TRIM(J17))=0,1,0) -> 0 | V17: =IF(AND(I17="Manual",C17<Parameters!$B$19,C17>=Parameters!$B$19*(1-Parameters!$B$20)),1,0) -> 0 | W17: =IF(AND(I17="Manual",M17>0),1,0) -> 0 | X17: =IF(A17-A16>1,1,0) -> 0 | Y17: =N17*Parameters!$B$38+O17*Parameters!$B$39+P17*Parameters!$B$40+Q17*Parameters!$B$41+R17*Parameters!$B$42+S17*Parameters!$B$43+T17*Parameters!$B$44+U17*Parameters!$B$45+V17*Parameters!$B$46+W17*Parameters!$B$47+X17*Parameters!$B$48 -> 0 | Z17: =IF(Y17>=Parameters!$B$25,"High","")
... A795: 1802 | B795: =COUNTIF(JE_Lines!$B$5:$B$1733,A795) -> 2 | C795: =SUMIFS(JE_Lines!$G$5:$G$1733,JE_Lines!$B$5:$B$1733,A795) -> 410000 | D795: =SUMIFS(JE_Lines!$H$5:$H$1733,JE_Lines!$B$5:$B$1733,A795) -> 410000 | E795: =C795-D795 -> 0 | F795: =INDEX(JE_Lines!$C$5:$C$1733,MATCH(A795,JE_Lines!$B$5:$B$1733,0)) -> 46022 | G795: =INDEX(JE_Lines!$D$5:$D$1733,MATCH(A795,JE_Lines!$B$5:$B$1733,0)) -> 46022 | H795: =INDEX(JE_Lines!$I$5:$I$1733,MATCH(A795,JE_Lines!$B$5:$B$1733,0)) -> FIN03 | I795: =INDEX(JE_Lines!$J$5:$J$1733,MATCH(A795,JE_Lines!$B$5:$B$1733,0)) -> Manual | J795: =IF(LEN(INDEX(JE_Lines!$K$5:$K$1733,MATCH(A795,JE_Lines!$B$5:$B$1733,0)))=0,"",INDEX(JE_Lines!$K$5:$K$1733,MATCH(A795,JE_Lines!$B$5:$B$1733,0))) | K795: =F795-G795 -> 0 | L795: =COUNTIFS(JE_Lines!$B$5:$B$1733,A795,JE_Lines!$F$5:$F$1733,"Revenue") -> 1 | M795: =COUNTIFS(JE_Lines!$B$5:$B$1733,A795,JE_Lines!$F$5:$F$1733,"Suspense") -> 0 | N795: =IF(ABS(E795)>Parameters!$B$23,1,0) -> 0 | O795: =IF(WEEKDAY(F795,2)>5,1,0) -> 0 | P795: =IF(K795>Parameters!$B$17,1,0) -> 0 | Q795: =IF(AND(F795<=Parameters!$B$6,F795>Parameters!$B$6-Parameters!$B$18),1,0) -> 1 | R795: =IF(COUNTIF(Parameters!$A$51:$A$58,H795)=0,1,0) -> 0 | S795: =IF(AND(I795="Manual",L795>0),1,0) -> 1 | T795: =IF(AND(C795>=Parameters!$B$22,ROUND(MOD(ROUND(C795,2),Parameters!$B$21),2)=0),1,0) -> 1 | U795: =IF(LEN(TRIM(J795))=0,1,0) -> 1 | V795: =IF(AND(I795="Manual",C795<Parameters!$B$19,C795>=Parameters!$B$19*(1-Parameters!$B$20)),1,0) -> 0 | W795: =IF(AND(I795="Manual",M795>0),1,0) -> 0 | X795: =IF(A795-A794>1,1,0) -> 0 | Y795: =N795*Parameters!$B$38+O795*Parameters!$B$39+P795*Parameters!$B$40+Q795*Parameters!$B$41+R795*Parameters!$B$42+S795*Parameters!$B$43+T795*Parameters!$B$44+U795*Parameters!$B$45+V795*Parameters!$B$46+W795*Parameters!$B$47+X795*Parameters!$B$48 -> 8 | Z795: =IF(Y795>=Parameters!$B$25,"High","") -> High

Sheet Answer_Key
A1: Answer key: seeded anomalies and known benign patterns
A2: Sample / demonstration data only. No real company, vendor, employee or transaction.
A3: For validation only. Detected? is a live lookup into the flag columns. Benign rows are expected false positives.
A4: Level | B4: ID | C4: Test key | D4: Category | E4: Note | F4: Detected?
A5: Payment | B5: P0001 | C5: p_rnd | D5: Benign by construction | E5: Monthly rent | F5: =IF(INDEX(Payments!$K$5:$K$634,MATCH(B5,Payments!$A$5:$A$634,0))=1,"Yes","No") -> Yes
A6: Payment | B6: P0002 | C6: p_rnd | D6: Seeded anomaly | E6: Round sum | F6: =IF(INDEX(Payments!$K$5:$K$634,MATCH(B6,Payments!$A$5:$A$634,0))=1,"Yes","No") -> Yes
A7: Payment | B7: P0012 | C7: p_dup | D7: Seeded anomaly | E7: Exact duplicate | F7: =IF(INDEX(Payments!$I$5:$I$634,MATCH(B7,Payments!$A$5:$A$634,0))=1,"Yes","No") -> Yes
A8: Payment | B8: P0024 | C8: p_below | D8: Seeded anomaly | E8: Threshold avoidance vendor | F8: =IF(INDEX(Payments!$L$5:$L$634,MATCH(B8,Payments!$A$5:$A$634,0))=1,"Yes","No") -> Yes
A9: Payment | B9: P0028 | C9: p_below | D9: Seeded anomaly | E9: Threshold avoidance vendor | F9: =IF(INDEX(Payments!$L$5:$L$634,MATCH(B9,Payments!$A$5:$A$634,0))=1,"Yes","No") -> No
A10: Payment | B10: P0033 | C10: p_below | D10: Benign by construction | E10: Monthly licence | F10: =IF(INDEX(Payments!$L$5:$L$634,MATCH(B10,Payments!$A$5:$A$634,0))=1,"Yes","No") -> Yes
A11: Payment | B11: P0038 | C11: p_below | D11: Seeded anomaly | E11: Threshold avoidance vendor | F11: =IF(INDEX(Payments!$L$5:$L$634,MATCH(B11,Payments!$A$5:$A$634,0))=1,"Yes","No") -> Yes
A12: Payment | B12: P0065 | C12: p_below | D12: Seeded anomaly | E12: Threshold avoidance vendor | F12: =IF(INDEX(Payments!$L$5:$L$634,MATCH(B12,Payments!$A$5:$A$634,0))=1,"Yes","No") -> Yes
A13: Payment | B13: P0066 | C13: p_rnd | D13: Benign by construction | E13: Monthly rent | F13: =IF(INDEX(Payments!$K$5:$K$634,MATCH(B13,Payments!$A$5:$A$634,0))=1,"Yes","No") -> Yes
A14: Payment | B14: P0066 | C14: p_near | D14: Benign by construction | E14: Monthly rent, same amount within the window | F14: =IF(INDEX(Payments!$J$5:$J$634,MATCH(B14,Payments!$A$5:$A$634,0))=1,"Yes","No") -> Yes
A15: Payment | B15: P0075 | C15: p_below | D15: Benign by construction | E15: Monthly licence | F15: =IF(INDEX(Payments!$L$5:$L$634,MATCH(B15,Payments!$A$5:$A$634,0))=1,"Yes","No") -> Yes
A16: Payment | B16: P0075 | C16: p_near | D16: Benign by construction | E16: Monthly licence, same amount within the window | F16: =IF(INDEX(Payments!$J$5:$J$634,MATCH(B16,Payments!$A$5:$A$634,0))=1,"Yes","No") -> Yes
A17: Payment | B17: P0081 | C17: p_below | D17: Seeded anomaly | E17: Threshold avoidance vendor | F17: =IF(INDEX(Payments!$L$5:$L$634,MATCH(B17,Payments!$A$5:$A$634,0))=1,"Yes","No") -> Yes
A18: Payment | B18: P0084 | C18: p_below | D18: Seeded anomaly | E18: Threshold avoidance vendor | F18: =IF(INDEX(Payments!$L$5:$L$634,MATCH(B18,Payments!$A$5:$A$634,0))=1,"Yes","No") -> Yes
A19: Payment | B19: P0097 | C19: p_below | D19: Seeded anomaly | E19: Threshold avoidance vendor | F19: =IF(INDEX(Payments!$L$5:$L$634,MATCH(B19,Payments!$A$5:$A$634,0))=1,"Yes","No") -> Yes
A20: Payment | B20: P0099 | C20: p_rnd | D20: Benign by construction | E20: Monthly rent | F20: =IF(INDEX(Payments!$K$5:$K$634,MATCH(B20,Payments!$A$5:$A$634,0))=1,"Yes","No") -> Yes
A21: Payment | B21: P0099 | C21: p_near | D21: Benign by construction | E21: Monthly rent, same amount within the window | F21: =IF(INDEX(Payments!$J$5:$J$634,MATCH(B21,Payments!$A$5:$A$634,0))=1,"Yes","No") -> Yes
A22: Payment | B22: P0104 | C22: p_below | D22: Seeded anomaly | E22: Threshold avoidance vendor | F22: =IF(INDEX(Payments!$L$5:$L$634,MATCH(B22,Payments!$A$5:$A$634,0))=1,"Yes","No") -> No
A23: Payment | B23: P0104 | C23: p_split | D23: Counterpart of seeded anomaly | E23: Same day collision of threshold avoidance payments | F23: =IF(INDEX(Payments!$M$5:$M$634,MATCH(B23,Payments!$A$5:$A$634,0))=1,"Yes","No") -> Yes
A24: Payment | B24: P0105 | C24: p_below | D24: Seeded anomaly | E24: Threshold avoidance vendor | F24: =IF(INDEX(Payments!$L$5:$L$634,MATCH(B24,Payments!$A$5:$A$634,0))=1,"Yes","No") -> Yes
A25: Payment | B25: P0105 | C25: p_split | D25: Counterpart of seeded anomaly | E25: Same day collision of threshold avoidance payments | F25: =IF(INDEX(Payments!$M$5:$M$634,MATCH(B25,Payments!$A$5:$A$634,0))=1,"Yes","No") -> Yes
A26: Payment | B26: P0106 | C26: p_below | D26: Seeded anomaly | E26: Threshold avoidance vendor | F26: =IF(INDEX(Payments!$L$5:$L$634,MATCH(B26,Payments!$A$5:$A$634,0))=1,"Yes","No") -> Yes
A27: Payment | B27: P0106 | C27: p_split | D27: Counterpart of seeded anomaly | E27: Same day collision of threshold avoidance payments | F27: =IF(INDEX(Payments!$M$5:$M$634,MATCH(B27,Payments!$A$5:$A$634,0))=1,"Yes","No") -> Yes
A28: Payment | B28: P0116 | C28: p_below | D28: Seeded anomaly | E28: Threshold avoidance vendor | F28: =IF(INDEX(Payments!$L$5:$L$634,MATCH(B28,Payments!$A$5:$A$634,0))=1,"Yes","No") -> Yes
A29: Payment | B29: P0118 | C29: p_below | D29: Seeded anomaly | E29: Threshold avoidance vendor | F29: =IF(INDEX(Payments!$L$5:$L$634,MATCH(B29,Payments!$A$5:$A$634,0))=1,"Yes","No") -> Yes
A30: Payment | B30: P0123 | C30: p_dup | D30: Seeded anomaly | E30: Exact duplicate | F30: =IF(INDEX(Payments!$I$5:$I$634,MATCH(B30,Payments!$A$5:$A$634,0))=1,"Yes","No") -> Yes
A31: Payment | B31: P0125 | C31: p_below | D31: Benign by construction | E31: Monthly licence | F31: =IF(INDEX(Payments!$L$5:$L$634,MATCH(B31,Payments!$A$5:$A$634,0))=1,"Yes","No") -> Yes
A32: Payment | B32: P0125 | C32: p_near | D32: Benign by construction | E32: Monthly licence, same amount within the window | F32: =IF(INDEX(Payments!$J$5:$J$634,MATCH(B32,Payments!$A$5:$A$634,0))=1,"Yes","No") -> Yes
A33: Payment | B33: P0139 | C33: p_rnd | D33: Benign by construction | E33: Monthly rent | F33: =IF(INDEX(Payments!$K$5:$K$634,MATCH(B33,Payments!$A$5:$A$634,0))=1,"Yes","No") -> Yes
A34: Payment | B34: P0139 | C34: p_near | D34: Benign by construction | E34: Monthly rent, same amount within the window | F34: =IF(INDEX(Payments!$J$5:$J$634,MATCH(B34,Payments!$A$5:$A$634,0))=1,"Yes","No") -> Yes
A35: Payment | B35: P0147 | C35: p_below | D35: Seeded anomaly | E35: Threshold avoidance vendor | F35: =IF(INDEX(Payments!$L$5:$L$634,MATCH(B35,Payments!$A$5:$A$634,0))=1,"Yes","No") -> Yes
A36: Payment | B36: P0149 | C36: p_below | D36: Seeded anomaly | E36: Threshold avoidance vendor | F36: =IF(INDEX(Payments!$L$5:$L$634,MATCH(B36,Payments!$A$5:$A$634,0))=1,"Yes","No") -> Yes
A37: Payment | B37: P0156 | C37: p_auth | D37: Seeded anomaly | E37: Approved below required authority | F37: =IF(INDEX(Payments!$N$5:$N$634,MATCH(B37,Payments!$A$5:$A$634,0))=1,"Yes","No") -> Yes
A38: Payment | B38: P0167 | C38: p_dup | D38: Seeded anomaly | E38: Duplicate, invoice number reformatted | F38: =IF(INDEX(Payments!$I$5:$I$634,MATCH(B38,Payments!$A$5:$A$634,0))=1,"Yes","No") -> Yes
A39: Payment | B39: P0175 | C39: p_below | D39: Seeded anomaly | E39: Threshold avoidance vendor | F39: =IF(INDEX(Payments!$L$5:$L$634,MATCH(B39,Payments!$A$5:$A$634,0))=1,"Yes","No") -> Yes
A40: Payment | B40: P0177 | C40: p_below | D40: Seeded anomaly | E40: Threshold avoidance vendor | F40: =IF(INDEX(Payments!$L$5:$L$634,MATCH(B40,Payments!$A$5:$A$634,0))=1,"Yes","No") -> Yes
A41: Payment | B41: P0179 | C41: p_below | D41: Benign by construction | E41: Monthly licence | F41: =IF(INDEX(Payments!$L$5:$L$634,MATCH(B41,Payments!$A$5:$A$634,0))=1,"Yes","No") -> Yes
A42: Payment | B42: P0179 | C42: p_near | D42: Benign by construction | E42: Monthly licence, same amount within the window | F42: =IF(INDEX(Payments!$J$5:$J$634,MATCH(B42,Payments!$A$5:$A$634,0))=1,"Yes","No") -> Yes
A43: Payment | B43: P0191 | C43: p_below | D43: Seeded anomaly | E43: Threshold avoidance vendor | F43: =IF(INDEX(Payments!$L$5:$L$634,MATCH(B43,Payments!$A$5:$A$634,0))=1,"Yes","No") -> Yes
A44: Payment | B44: P0195 | C44: p_below | D44: Seeded anomaly | E44: Threshold avoidance vendor | F44: =IF(INDEX(Payments!$L$5:$L$634,MATCH(B44,Payments!$A$5:$A$634,0))=1,"Yes","No") -> Yes
A45: Payment | B45: P0195 | C45: p_split | D45: Counterpart of seeded anomaly | E45: Same day collision of threshold avoidance payments | F45: =IF(INDEX(Payments!$M$5:$M$634,MATCH(B45,Payments!$A$5:$A$634,0))=1,"Yes","No") -> Yes
A46: Payment | B46: P0196 | C46: p_below | D46: Seeded anomaly | E46: Threshold avoidance vendor | F46: =IF(INDEX(Payments!$L$5:$L$634,MATCH(B46,Payments!$A$5:$A$634,0))=1,"Yes","No") -> Yes
A47: Payment | B47: P0196 | C47: p_split | D47: Counterpart of seeded anomaly | E47: Same day collision of threshold avoidance payments | F47: =IF(INDEX(Payments!$M$5:$M$634,MATCH(B47,Payments!$A$5:$A$634,0))=1,"Yes","No") -> Yes
A48: Payment | B48: P0198 | C48: p_rnd | D48: Seeded anomaly | E48: Round sum | F48: =IF(INDEX(Payments!$K$5:$K$634,MATCH(B48,Payments!$A$5:$A$634,0))=1,"Yes","No") -> Yes
A49: Payment | B49: P0202 | C49: p_rnd | D49: Seeded anomaly | E49: Round sum | F49: =IF(INDEX(Payments!$K$5:$K$634,MATCH(B49,Payments!$A$5:$A$634,0))=1,"Yes","No") -> Yes
A50: Payment | B50: P0213 | C50: p_rnd | D50: Benign by construction | E50: Monthly rent | F50: =IF(INDEX(Payments!$K$5:$K$634,MATCH(B50,Payments!$A$5:$A$634,0))=1,"Yes","No") -> Yes
A51: Payment | B51: P0213 | C51: p_near | D51: Benign by construction | E51: Monthly rent, same amount within the window | F51: =IF(INDEX(Payments!$J$5:$J$634,MATCH(B51,Payments!$A$5:$A$634,0))=1,"Yes","No") -> Yes
A52: Payment | B52: P0220 | C52: p_below | D52: Seeded anomaly | E52: Threshold avoidance vendor | F52: =IF(INDEX(Payments!$L$5:$L$634,MATCH(B52,Payments!$A$5:$A$634,0))=1,"Yes","No") -> Yes
A53: Payment | B53: P0223 | C53: p_below | D53: Seeded anomaly | E53: Threshold avoidance vendor | F53: =IF(INDEX(Payments!$L$5:$L$634,MATCH(B53,Payments!$A$5:$A$634,0))=1,"Yes","No") -> Yes
A54: Payment | B54: P0224 | C54: p_rnd | D54: Seeded anomaly | E54: Round sum | F54: =IF(INDEX(Payments!$K$5:$K$634,MATCH(B54,Payments!$A$5:$A$634,0))=1,"Yes","No") -> Yes
A55: Payment | B55: P0233 | C55: p_below | D55: Benign by construction | E55: Monthly licence | F55: =IF(INDEX(Payments!$L$5:$L$634,MATCH(B55,Payments!$A$5:$A$634,0))=1,"Yes","No") -> Yes
A56: Payment | B56: P0233 | C56: p_near | D56: Benign by construction | E56: Monthly licence, same amount within the window | F56: =IF(INDEX(Payments!$J$5:$J$634,MATCH(B56,Payments!$A$5:$A$634,0))=1,"Yes","No") -> Yes
A57: Payment | B57: P0234 | C57: p_split | D57: Seeded anomaly | E57: Same day split | F57: =IF(INDEX(Payments!$M$5:$M$634,MATCH(B57,Payments!$A$5:$A$634,0))=1,"Yes","No") -> Yes
A58: Payment | B58: P0235 | C58: p_split | D58: Seeded anomaly | E58: Same day split | F58: =IF(INDEX(Payments!$M$5:$M$634,MATCH(B58,Payments!$A$5:$A$634,0))=1,"Yes","No") -> Yes
A59: Payment | B59: P0243 | C59: p_below | D59: Seeded anomaly | E59: Threshold avoidance vendor | F59: =IF(INDEX(Payments!$L$5:$L$634,MATCH(B59,Payments!$A$5:$A$634,0))=1,"Yes","No") -> Yes
A60: Payment | B60: P0248 | C60: p_below | D60: Seeded anomaly | E60: Threshold avoidance vendor | F60: =IF(INDEX(Payments!$L$5:$L$634,MATCH(B60,Payments!$A$5:$A$634,0))=1,"Yes","No") -> Yes
A61: Payment | B61: P0262 | C61: p_rnd | D61: Benign by construction | E61: Monthly rent | F61: =IF(INDEX(Payments!$K$5:$K$634,MATCH(B61,Payments!$A$5:$A$634,0))=1,"Yes","No") -> Yes
A62: Payment | B62: P0262 | C62: p_near | D62: Benign by construction | E62: Monthly rent, same amount within the window | F62: =IF(INDEX(Payments!$J$5:$J$634,MATCH(B62,Payments!$A$5:$A$634,0))=1,"Yes","No") -> Yes
A63: Payment | B63: P0263 | C63: p_near | D63: Counterpart of seeded anomaly | F63: =IF(INDEX(Payments!$J$5:$J$634,MATCH(B63,Payments!$A$5:$A$634,0))=1,"Yes","No") -> Yes
A64: Payment | B64: P0265 | C64: p_below | D64: Seeded anomaly | E64: Threshold avoidance vendor | F64: =IF(INDEX(Payments!$L$5:$L$634,MATCH(B64,Payments!$A$5:$A$634,0))=1,"Yes","No") -> Yes
A65: Payment | B65: P0267 | C65: p_below | D65: Seeded anomaly | E65: Threshold avoidance vendor | F65: =IF(INDEX(Payments!$L$5:$L$634,MATCH(B65,Payments!$A$5:$A$634,0))=1,"Yes","No") -> Yes
A66: Payment | B66: P0271 | C66: p_dup | D66: Seeded anomaly | E66: Exact duplicate | F66: =IF(INDEX(Payments!$I$5:$I$634,MATCH(B66,Payments!$A$5:$A$634,0))=1,"Yes","No") -> Yes
A67: Payment | B67: P0272 | C67: p_near | D67: Seeded anomaly | E67: Same amount, new invoice number | F67: =IF(INDEX(Payments!$J$5:$J$634,MATCH(B67,Payments!$A$5:$A$634,0))=1,"Yes","No") -> Yes
A68: Payment | B68: P0275 | C68: p_auth | D68: Seeded anomaly | E68: Approved below required authority | F68: =IF(INDEX(Payments!$N$5:$N$634,MATCH(B68,Payments!$A$5:$A$634,0))=1,"Yes","No") -> Yes
A69: Payment | B69: P0288 | C69: p_below | D69: Benign by construction | E69: Monthly licence | F69: =IF(INDEX(Payments!$L$5:$L$634,MATCH(B69,Payments!$A$5:$A$634,0))=1,"Yes","No") -> Yes
A70: Payment | B70: P0296 | C70: p_below | D70: Seeded anomaly | E70: Threshold avoidance vendor | F70: =IF(INDEX(Payments!$L$5:$L$634,MATCH(B70,Payments!$A$5:$A$634,0))=1,"Yes","No") -> Yes
A71: Payment | B71: P0309 | C71: p_rnd | D71: Benign by construction | E71: Monthly rent | F71: =IF(INDEX(Payments!$K$5:$K$634,MATCH(B71,Payments!$A$5:$A$634,0))=1,"Yes","No") -> Yes
A72: Payment | B72: P0309 | C72: p_near | D72: Benign by construction | E72: Monthly rent, same amount within the window | F72: =IF(INDEX(Payments!$J$5:$J$634,MATCH(B72,Payments!$A$5:$A$634,0))=1,"Yes","No") -> Yes
A73: Payment | B73: P0319 | C73: p_below | D73: Seeded anomaly | E73: Threshold avoidance vendor | F73: =IF(INDEX(Payments!$L$5:$L$634,MATCH(B73,Payments!$A$5:$A$634,0))=1,"Yes","No") -> No
A74: Payment | B74: P0324 | C74: p_below | D74: Benign by construction | E74: Monthly licence | F74: =IF(INDEX(Payments!$L$5:$L$634,MATCH(B74,Payments!$A$5:$A$634,0))=1,"Yes","No") -> Yes
A75: Payment | B75: P0340 | C75: p_below | D75: Seeded anomaly | E75: Threshold avoidance vendor | F75: =IF(INDEX(Payments!$L$5:$L$634,MATCH(B75,Payments!$A$5:$A$634,0))=1,"Yes","No") -> Yes
A76: Payment | B76: P0348 | C76: p_near | D76: Counterpart of seeded anomaly | F76: =IF(INDEX(Payments!$J$5:$J$634,MATCH(B76,Payments!$A$5:$A$634,0))=1,"Yes","No") -> Yes
A77: Payment | B77: P0351 | C77: p_rnd | D77: Benign by construction | E77: Monthly rent | F77: =IF(INDEX(Payments!$K$5:$K$634,MATCH(B77,Payments!$A$5:$A$634,0))=1,"Yes","No") -> Yes
A78: Payment | B78: P0353 | C78: p_below | D78: Seeded anomaly | E78: Threshold avoidance vendor | F78: =IF(INDEX(Payments!$L$5:$L$634,MATCH(B78,Payments!$A$5:$A$634,0))=1,"Yes","No") -> Yes
A79: Payment | B79: P0353 | C79: p_split | D79: Counterpart of seeded anomaly | E79: Same day collision of threshold avoidance payments | F79: =IF(INDEX(Payments!$M$5:$M$634,MATCH(B79,Payments!$A$5:$A$634,0))=1,"Yes","No") -> Yes
A80: Payment | B80: P0354 | C80: p_below | D80: Seeded anomaly | E80: Threshold avoidance vendor | F80: =IF(INDEX(Payments!$L$5:$L$634,MATCH(B80,Payments!$A$5:$A$634,0))=1,"Yes","No") -> Yes
A81: Payment | B81: P0354 | C81: p_split | D81: Counterpart of seeded anomaly | E81: Same day collision of threshold avoidance payments | F81: =IF(INDEX(Payments!$M$5:$M$634,MATCH(B81,Payments!$A$5:$A$634,0))=1,"Yes","No") -> Yes
A82: Payment | B82: P0358 | C82: p_split | D82: Seeded anomaly | E82: Same day split | F82: =IF(INDEX(Payments!$M$5:$M$634,MATCH(B82,Payments!$A$5:$A$634,0))=1,"Yes","No") -> Yes
A83: Payment | B83: P0359 | C83: p_split | D83: Seeded anomaly | E83: Same day split | F83: =IF(INDEX(Payments!$M$5:$M$634,MATCH(B83,Payments!$A$5:$A$634,0))=1,"Yes","No") -> Yes
A84: Payment | B84: P0360 | C84: p_split | D84: Seeded anomaly | E84: Same day split | F84: =IF(INDEX(Payments!$M$5:$M$634,MATCH(B84,Payments!$A$5:$A$634,0))=1,"Yes","No") -> Yes
A85: Payment | B85: P0368 | C85: p_auth | D85: Seeded anomaly | E85: Approved below required authority | F85: =IF(INDEX(Payments!$N$5:$N$634,MATCH(B85,Payments!$A$5:$A$634,0))=1,"Yes","No") -> Yes
A86: Payment | B86: P0369 | C86: p_below | D86: Seeded anomaly | E86: Threshold avoidance vendor | F86: =IF(INDEX(Payments!$L$5:$L$634,MATCH(B86,Payments!$A$5:$A$634,0))=1,"Yes","No") -> Yes
A87: Payment | B87: P0373 | C87: p_below | D87: Seeded anomaly | E87: Threshold avoidance vendor | F87: =IF(INDEX(Payments!$L$5:$L$634,MATCH(B87,Payments!$A$5:$A$634,0))=1,"Yes","No") -> Yes
A88: Payment | B88: P0378 | C88: p_below | D88: Benign by construction | E88: Monthly licence | F88: =IF(INDEX(Payments!$L$5:$L$634,MATCH(B88,Payments!$A$5:$A$634,0))=1,"Yes","No") -> Yes
A89: Payment | B89: P0378 | C89: p_near | D89: Benign by construction | E89: Monthly licence, same amount within the window | F89: =IF(INDEX(Payments!$J$5:$J$634,MATCH(B89,Payments!$A$5:$A$634,0))=1,"Yes","No") -> Yes
A90: Payment | B90: P0381 | C90: p_near | D90: Seeded anomaly | E90: Same amount, new invoice number | F90: =IF(INDEX(Payments!$J$5:$J$634,MATCH(B90,Payments!$A$5:$A$634,0))=1,"Yes","No") -> Yes
A91: Payment | B91: P0390 | C91: p_below | D91: Seeded anomaly | E91: Threshold avoidance vendor | F91: =IF(INDEX(Payments!$L$5:$L$634,MATCH(B91,Payments!$A$5:$A$634,0))=1,"Yes","No") -> Yes
A92: Payment | B92: P0394 | C92: p_rnd | D92: Seeded anomaly | E92: Round sum | F92: =IF(INDEX(Payments!$K$5:$K$634,MATCH(B92,Payments!$A$5:$A$634,0))=1,"Yes","No") -> Yes
A93: Payment | B93: P0406 | C93: p_split | D93: Seeded anomaly | E93: Same day split | F93: =IF(INDEX(Payments!$M$5:$M$634,MATCH(B93,Payments!$A$5:$A$634,0))=1,"Yes","No") -> Yes
A94: Payment | B94: P0407 | C94: p_split | D94: Seeded anomaly | E94: Same day split | F94: =IF(INDEX(Payments!$M$5:$M$634,MATCH(B94,Payments!$A$5:$A$634,0))=1,"Yes","No") -> Yes
A95: Payment | B95: P0408 | C95: p_below | D95: Seeded anomaly | E95: Threshold avoidance vendor | F95: =IF(INDEX(Payments!$L$5:$L$634,MATCH(B95,Payments!$A$5:$A$634,0))=1,"Yes","No") -> Yes
A96: Payment | B96: P0411 | C96: p_rnd | D96: Seeded anomaly | E96: Round sum | F96: =IF(INDEX(Payments!$K$5:$K$634,MATCH(B96,Payments!$A$5:$A$634,0))=1,"Yes","No") -> Yes
A97: Payment | B97: P0415 | C97: p_rnd | D97: Benign by construction | E97: Monthly rent | F97: =IF(INDEX(Payments!$K$5:$K$634,MATCH(B97,Payments!$A$5:$A$634,0))=1,"Yes","No") -> Yes
A98: Payment | B98: P0420 | C98: p_rnd | D98: Seeded anomaly | E98: Round sum | F98: =IF(INDEX(Payments!$K$5:$K$634,MATCH(B98,Payments!$A$5:$A$634,0))=1,"Yes","No") -> Yes
A99: Payment | B99: P0425 | C99: p_split | D99: Seeded anomaly | E99: Same day split | F99: =IF(INDEX(Payments!$M$5:$M$634,MATCH(B99,Payments!$A$5:$A$634,0))=1,"Yes","No") -> Yes
A100: Payment | B100: P0426 | C100: p_split | D100: Seeded anomaly | E100: Same day split | F100: =IF(INDEX(Payments!$M$5:$M$634,MATCH(B100,Payments!$A$5:$A$634,0))=1,"Yes","No") -> Yes
...

Sheet Exceptions
A1: Exceptions summary and High risk lists
A2: Sample / demonstration data only. No real company, vendor, employee or transaction.
A3: Recall is measured against the answer key. Flagged but not in key = items a reviewer must clear.
A4: Test key | B4: Test | C4: Population | D4: Flagged | E4: Flag rate | F4: Seeded anomalies | G4: Seeded detected | H4: Recall | I4: Flagged, not in answer key
A5: p_dup | B5: Duplicate payment (vendor, normalised invoice, amount) | C5: =COUNTA(Payments!$A$5:$A$634) -> 630 | D5: =SUM(Payments!$I$5:$I$634) -> 10 | E5: =D5/C5 -> 0.015873016 | F5: =COUNTIFS(Answer_Key!$C$5:$C$261,A5,Answer_Key!$D$5:$D$261,"Seeded anomaly") -> 10 | G5: =COUNTIFS(Answer_Key!$C$5:$C$261,A5,Answer_Key!$D$5:$D$261,"Seeded anomaly",Answer_Key!$F$5:$F$261,"Yes") -> 10 | H5: =IF(F5=0,"n/a",G5/F5) -> 1 | I5: =D5-COUNTIFS(Answer_Key!$C$5:$C$261,A5,Answer_Key!$F$5:$F$261,"Yes") -> 0
A6: p_near | B6: Near duplicate payment | C6: =COUNTA(Payments!$A$5:$A$634) -> 630 | D6: =SUM(Payments!$J$5:$J$634) -> 25 | E6: =D6/C6 -> 0.03968254 | F6: =COUNTIFS(Answer_Key!$C$5:$C$261,A6,Answer_Key!$D$5:$D$261,"Seeded anomaly") -> 4 | G6: =COUNTIFS(Answer_Key!$C$5:$C$261,A6,Answer_Key!$D$5:$D$261,"Seeded anomaly",Answer_Key!$F$5:$F$261,"Yes") -> 4 | H6: =IF(F6=0,"n/a",G6/F6) -> 1 | I6: =D6-COUNTIFS(Answer_Key!$C$5:$C$261,A6,Answer_Key!$F$5:$F$261,"Yes") -> 0
A7: p_rnd | B7: Round sum payment | C7: =COUNTA(Payments!$A$5:$A$634) -> 630 | D7: =SUM(Payments!$K$5:$K$634) -> 24 | E7: =D7/C7 -> 0.038095238 | F7: =COUNTIFS(Answer_Key!$C$5:$C$261,A7,Answer_Key!$D$5:$D$261,"Seeded anomaly") -> 12 | G7: =COUNTIFS(Answer_Key!$C$5:$C$261,A7,Answer_Key!$D$5:$D$261,"Seeded anomaly",Answer_Key!$F$5:$F$261,"Yes") -> 12 | H7: =IF(F7=0,"n/a",G7/F7) -> 1 | I7: =D7-COUNTIFS(Answer_Key!$C$5:$C$261,A7,Answer_Key!$F$5:$F$261,"Yes") -> 0
A8: p_below | B8: Payment just below approval limit | C8: =COUNTA(Payments!$A$5:$A$634) -> 630 | D8: =SUM(Payments!$L$5:$L$634) -> 55 | E8: =D8/C8 -> 0.087301587 | F8: =COUNTIFS(Answer_Key!$C$5:$C$261,A8,Answer_Key!$D$5:$D$261,"Seeded anomaly") -> 45 | G8: =COUNTIFS(Answer_Key!$C$5:$C$261,A8,Answer_Key!$D$5:$D$261,"Seeded anomaly",Answer_Key!$F$5:$F$261,"Yes") -> 39 | H8: =IF(F8=0,"n/a",G8/F8) -> 0.86666667 | I8: =D8-COUNTIFS(Answer_Key!$C$5:$C$261,A8,Answer_Key!$F$5:$F$261,"Yes") -> 4
A9: p_split | B9: Same day split payments above limit | C9: =COUNTA(Payments!$A$5:$A$634) -> 630 | D9: =SUM(Payments!$M$5:$M$634) -> 34 | E9: =D9/C9 -> 0.053968254 | F9: =COUNTIFS(Answer_Key!$C$5:$C$261,A9,Answer_Key!$D$5:$D$261,"Seeded anomaly") -> 12 | G9: =COUNTIFS(Answer_Key!$C$5:$C$261,A9,Answer_Key!$D$5:$D$261,"Seeded anomaly",Answer_Key!$F$5:$F$261,"Yes") -> 12 | H9: =IF(F9=0,"n/a",G9/F9) -> 1 | I9: =D9-COUNTIFS(Answer_Key!$C$5:$C$261,A9,Answer_Key!$F$5:$F$261,"Yes") -> 10
A10: p_auth | B10: Approved below required authority | C10: =COUNTA(Payments!$A$5:$A$634) -> 630 | D10: =SUM(Payments!$N$5:$N$634) -> 3 | E10: =D10/C10 -> 0.0047619048 | F10: =COUNTIFS(Answer_Key!$C$5:$C$261,A10,Answer_Key!$D$5:$D$261,"Seeded anomaly") -> 3 | G10: =COUNTIFS(Answer_Key!$C$5:$C$261,A10,Answer_Key!$D$5:$D$261,"Seeded anomaly",Answer_Key!$F$5:$F$261,"Yes") -> 3 | H10: =IF(F10=0,"n/a",G10/F10) -> 1 | I10: =D10-COUNTIFS(Answer_Key!$C$5:$C$261,A10,Answer_Key!$F$5:$F$261,"Yes") -> 0
A11: v_benf | B11: Vendor fails Benford test | C11: =COUNTA(Vendor_Benford!$A$6:$A$50) -> 45 | D11: =SUM(Vendor_Benford!$M$6:$M$50) -> 1 | E11: =D11/C11 -> 0.022222222 | F11: =COUNTIFS(Answer_Key!$C$5:$C$261,A11,Answer_Key!$D$5:$D$261,"Seeded anomaly") -> 1 | G11: =COUNTIFS(Answer_Key!$C$5:$C$261,A11,Answer_Key!$D$5:$D$261,"Seeded anomaly",Answer_Key!$F$5:$F$261,"Yes") -> 1 | H11: =IF(F11=0,"n/a",G11/F11) -> 1 | I11: =D11-COUNTIFS(Answer_Key!$C$5:$C$261,A11,Answer_Key!$F$5:$F$261,"Yes") -> 0
A12: v_emp | B12: Vendor bank account matches employee | C12: =COUNTA(Vendor_Benford!$A$6:$A$50) -> 45 | D12: =SUM(Vendor_Benford!$N$6:$N$50) -> 1 | E12: =D12/C12 -> 0.022222222 | F12: =COUNTIFS(Answer_Key!$C$5:$C$261,A12,Answer_Key!$D$5:$D$261,"Seeded anomaly") -> 1 | G12: =COUNTIFS(Answer_Key!$C$5:$C$261,A12,Answer_Key!$D$5:$D$261,"Seeded anomaly",Answer_Key!$F$5:$F$261,"Yes") -> 1 | H12: =IF(F12=0,"n/a",G12/F12) -> 1 | I12: =D12-COUNTIFS(Answer_Key!$C$5:$C$261,A12,Answer_Key!$F$5:$F$261,"Yes") -> 0
A13: j_unb | B13: Unbalanced journal entry | C13: =COUNTA(JE_Entries!$A$5:$A$795) -> 791 | D13: =SUM(JE_Entries!$N$5:$N$795) -> 3 | E13: =D13/C13 -> 0.0037926675 | F13: =COUNTIFS(Answer_Key!$C$5:$C$261,A13,Answer_Key!$D$5:$D$261,"Seeded anomaly") -> 3 | G13: =COUNTIFS(Answer_Key!$C$5:$C$261,A13,Answer_Key!$D$5:$D$261,"Seeded anomaly",Answer_Key!$F$5:$F$261,"Yes") -> 3 | H13: =IF(F13=0,"n/a",G13/F13) -> 1 | I13: =D13-COUNTIFS(Answer_Key!$C$5:$C$261,A13,Answer_Key!$F$5:$F$261,"Yes") -> 0
A14: j_wkd | B14: Posted on a weekend | C14: =COUNTA(JE_Entries!$A$5:$A$795) -> 791 | D14: =SUM(JE_Entries!$O$5:$O$795) -> 31 | E14: =D14/C14 -> 0.039190898 | F14: =COUNTIFS(Answer_Key!$C$5:$C$261,A14,Answer_Key!$D$5:$D$261,"Seeded anomaly") -> 8 | G14: =COUNTIFS(Answer_Key!$C$5:$C$261,A14,Answer_Key!$D$5:$D$261,"Seeded anomaly",Answer_Key!$F$5:$F$261,"Yes") -> 8 | H14: =IF(F14=0,"n/a",G14/F14) -> 1 | I14: =D14-COUNTIFS(Answer_Key!$C$5:$C$261,A14,Answer_Key!$F$5:$F$261,"Yes") -> 0
A15: j_late | B15: Late posting versus document date | C15: =COUNTA(JE_Entries!$A$5:$A$795) -> 791 | D15: =SUM(JE_Entries!$P$5:$P$795) -> 6 | E15: =D15/C15 -> 0.007585335 | F15: =COUNTIFS(Answer_Key!$C$5:$C$261,A15,Answer_Key!$D$5:$D$261,"Seeded anomaly") -> 6 | G15: =COUNTIFS(Answer_Key!$C$5:$C$261,A15,Answer_Key!$D$5:$D$261,"Seeded anomaly",Answer_Key!$F$5:$F$261,"Yes") -> 6 | H15: =IF(F15=0,"n/a",G15/F15) -> 1 | I15: =D15-COUNTIFS(Answer_Key!$C$5:$C$261,A15,Answer_Key!$F$5:$F$261,"Yes") -> 0
A16: j_pend | B16: Posted in last days of the year | C16: =COUNTA(JE_Entries!$A$5:$A$795) -> 791 | D16: =SUM(JE_Entries!$Q$5:$Q$795) -> 17 | E16: =D16/C16 -> 0.021491783 | F16: =COUNTIFS(Answer_Key!$C$5:$C$261,A16,Answer_Key!$D$5:$D$261,"Seeded anomaly") -> 5 | G16: =COUNTIFS(Answer_Key!$C$5:$C$261,A16,Answer_Key!$D$5:$D$261,"Seeded anomaly",Answer_Key!$F$5:$F$261,"Yes") -> 5 | H16: =IF(F16=0,"n/a",G16/F16) -> 1 | I16: =D16-COUNTIFS(Answer_Key!$C$5:$C$261,A16,Answer_Key!$F$5:$F$261,"Yes") -> 12
A17: j_unauth | B17: Posted by unauthorised user | C17: =COUNTA(JE_Entries!$A$5:$A$795) -> 791 | D17: =SUM(JE_Entries!$R$5:$R$795) -> 5 | E17: =D17/C17 -> 0.0063211125 | F17: =COUNTIFS(Answer_Key!$C$5:$C$261,A17,Answer_Key!$D$5:$D$261,"Seeded anomaly") -> 5 | G17: =COUNTIFS(Answer_Key!$C$5:$C$261,A17,Answer_Key!$D$5:$D$261,"Seeded anomaly",Answer_Key!$F$5:$F$261,"Yes") -> 5 | H17: =IF(F17=0,"n/a",G17/F17) -> 1 | I17: =D17-COUNTIFS(Answer_Key!$C$5:$C$261,A17,Answer_Key!$F$5:$F$261,"Yes") -> 0
A18: j_mrev | B18: Manual entry to revenue | C18: =COUNTA(JE_Entries!$A$5:$A$795) -> 791 | D18: =SUM(JE_Entries!$S$5:$S$795) -> 5 | E18: =D18/C18 -> 0.0063211125 | F18: =COUNTIFS(Answer_Key!$C$5:$C$261,A18,Answer_Key!$D$5:$D$261,"Seeded anomaly") -> 5 | G18: =COUNTIFS(Answer_Key!$C$5:$C$261,A18,Answer_Key!$D$5:$D$261,"Seeded anomaly",Answer_Key!$F$5:$F$261,"Yes") -> 5 | H18: =IF(F18=0,"n/a",G18/F18) -> 1 | I18: =D18-COUNTIFS(Answer_Key!$C$5:$C$261,A18,Answer_Key!$F$5:$F$261,"Yes") -> 0
A19: j_rnd | B19: Round total entry | C19: =COUNTA(JE_Entries!$A$5:$A$795) -> 791 | D19: =SUM(JE_Entries!$T$5:$T$795) -> 23 | E19: =D19/C19 -> 0.029077118 | F19: =COUNTIFS(Answer_Key!$C$5:$C$261,A19,Answer_Key!$D$5:$D$261,"Seeded anomaly") -> 11 | G19: =COUNTIFS(Answer_Key!$C$5:$C$261,A19,Answer_Key!$D$5:$D$261,"Seeded anomaly",Answer_Key!$F$5:$F$261,"Yes") -> 11 | H19: =IF(F19=0,"n/a",G19/F19) -> 1 | I19: =D19-COUNTIFS(Answer_Key!$C$5:$C$261,A19,Answer_Key!$F$5:$F$261,"Yes") -> 0
A20: j_nodesc | B20: Entry without description | C20: =COUNTA(JE_Entries!$A$5:$A$795) -> 791 | D20: =SUM(JE_Entries!$U$5:$U$795) -> 19 | E20: =D20/C20 -> 0.024020228 | F20: =COUNTIFS(Answer_Key!$C$5:$C$261,A20,Answer_Key!$D$5:$D$261,"Seeded anomaly") -> 9 | G20: =COUNTIFS(Answer_Key!$C$5:$C$261,A20,Answer_Key!$D$5:$D$261,"Seeded anomaly",Answer_Key!$F$5:$F$261,"Yes") -> 9 | H20: =IF(F20=0,"n/a",G20/F20) -> 1 | I20: =D20-COUNTIFS(Answer_Key!$C$5:$C$261,A20,Answer_Key!$F$5:$F$261,"Yes") -> 0
A21: j_below | B21: Manual entry just below approval limit | C21: =COUNTA(JE_Entries!$A$5:$A$795) -> 791 | D21: =SUM(JE_Entries!$V$5:$V$795) -> 6 | E21: =D21/C21 -> 0.007585335 | F21: =COUNTIFS(Answer_Key!$C$5:$C$261,A21,Answer_Key!$D$5:$D$261,"Seeded anomaly") -> 5 | G21: =COUNTIFS(Answer_Key!$C$5:$C$261,A21,Answer_Key!$D$5:$D$261,"Seeded anomaly",Answer_Key!$F$5:$F$261,"Yes") -> 5 | H21: =IF(F21=0,"n/a",G21/F21) -> 1 | I21: =D21-COUNTIFS(Answer_Key!$C$5:$C$261,A21,Answer_Key!$F$5:$F$261,"Yes") -> 1
A22: j_susp | B22: Manual entry to suspense | C22: =COUNTA(JE_Entries!$A$5:$A$795) -> 791 | D22: =SUM(JE_Entries!$W$5:$W$795) -> 4 | E22: =D22/C22 -> 0.00505689 | F22: =COUNTIFS(Answer_Key!$C$5:$C$261,A22,Answer_Key!$D$5:$D$261,"Seeded anomaly") -> 4 | G22: =COUNTIFS(Answer_Key!$C$5:$C$261,A22,Answer_Key!$D$5:$D$261,"Seeded anomaly",Answer_Key!$F$5:$F$261,"Yes") -> 4 | H22: =IF(F22=0,"n/a",G22/F22) -> 1 | I22: =D22-COUNTIFS(Answer_Key!$C$5:$C$261,A22,Answer_Key!$F$5:$F$261,"Yes") -> 0
A23: j_gap | B23: Sequence gap before entry | C23: =COUNTA(JE_Entries!$A$5:$A$795) -> 791 | D23: =SUM(JE_Entries!$X$5:$X$795) -> 6 | E23: =D23/C23 -> 0.007585335 | F23: =COUNTIFS(Answer_Key!$C$5:$C$261,A23,Answer_Key!$D$5:$D$261,"Seeded anomaly") -> 6 | G23: =COUNTIFS(Answer_Key!$C$5:$C$261,A23,Answer_Key!$D$5:$D$261,"Seeded anomaly",Answer_Key!$F$5:$F$261,"Yes") -> 6 | H23: =IF(F23=0,"n/a",G23/F23) -> 1 | I23: =D23-COUNTIFS(Answer_Key!$C$5:$C$261,A23,Answer_Key!$F$5:$F$261,"Yes") -> 0
A25: High risk payments (ranked by engine, details are formulas)
A26: Payment ID | B26: Vendor | C26: Date | D26: Amount (USD) | E26: Score | F26: Reviewer disposition (input)
A27: P0105 | B27: =INDEX(Payments!$C$5:$C$634,MATCH($A27,Payments!$A$5:$A$634,0)) -> V031 | C27: =INDEX(Payments!$B$5:$B$634,MATCH($A27,Payments!$A$5:$A$634,0)) -> 45720 | D27: =INDEX(Payments!$E$5:$E$634,MATCH($A27,Payments!$A$5:$A$634,0)) -> 4776.69 | E27: =INDEX(Payments!$Q$5:$Q$634,MATCH($A27,Payments!$A$5:$A$634,0)) -> 7
A28: P0106 | B28: =INDEX(Payments!$C$5:$C$634,MATCH($A28,Payments!$A$5:$A$634,0)) -> V031 | C28: =INDEX(Payments!$B$5:$B$634,MATCH($A28,Payments!$A$5:$A$634,0)) -> 45720 | D28: =INDEX(Payments!$E$5:$E$634,MATCH($A28,Payments!$A$5:$A$634,0)) -> 4781.77 | E28: =INDEX(Payments!$Q$5:$Q$634,MATCH($A28,Payments!$A$5:$A$634,0)) -> 7
A29: P0195 | B29: =INDEX(Payments!$C$5:$C$634,MATCH($A29,Payments!$A$5:$A$634,0)) -> V031 | C29: =INDEX(Payments!$B$5:$B$634,MATCH($A29,Payments!$A$5:$A$634,0)) -> 45771 | D29: =INDEX(Payments!$E$5:$E$634,MATCH($A29,Payments!$A$5:$A$634,0)) -> 4754.27 | E29: =INDEX(Payments!$Q$5:$Q$634,MATCH($A29,Payments!$A$5:$A$634,0)) -> 7
A30: P0196 | B30: =INDEX(Payments!$C$5:$C$634,MATCH($A30,Payments!$A$5:$A$634,0)) -> V031 | C30: =INDEX(Payments!$B$5:$B$634,MATCH($A30,Payments!$A$5:$A$634,0)) -> 45771 | D30: =INDEX(Payments!$E$5:$E$634,MATCH($A30,Payments!$A$5:$A$634,0)) -> 4869.87 | E30: =INDEX(Payments!$Q$5:$Q$634,MATCH($A30,Payments!$A$5:$A$634,0)) -> 7
A31: P0353 | B31: =INDEX(Payments!$C$5:$C$634,MATCH($A31,Payments!$A$5:$A$634,0)) -> V031 | C31: =INDEX(Payments!$B$5:$B$634,MATCH($A31,Payments!$A$5:$A$634,0)) -> 45873 | D31: =INDEX(Payments!$E$5:$E$634,MATCH($A31,Payments!$A$5:$A$634,0)) -> 4874.02 | E31: =INDEX(Payments!$Q$5:$Q$634,MATCH($A31,Payments!$A$5:$A$634,0)) -> 7
A32: P0354 | B32: =INDEX(Payments!$C$5:$C$634,MATCH($A32,Payments!$A$5:$A$634,0)) -> V031 | C32: =INDEX(Payments!$B$5:$B$634,MATCH($A32,Payments!$A$5:$A$634,0)) -> 45873 | D32: =INDEX(Payments!$E$5:$E$634,MATCH($A32,Payments!$A$5:$A$634,0)) -> 4837.05 | E32: =INDEX(Payments!$Q$5:$Q$634,MATCH($A32,Payments!$A$5:$A$634,0)) -> 7
A33: P0512 | B33: =INDEX(Payments!$C$5:$C$634,MATCH($A33,Payments!$A$5:$A$634,0)) -> V031 | C33: =INDEX(Payments!$B$5:$B$634,MATCH($A33,Payments!$A$5:$A$634,0)) -> 45958 | D33: =INDEX(Payments!$E$5:$E$634,MATCH($A33,Payments!$A$5:$A$634,0)) -> 4926.23 | E33: =INDEX(Payments!$Q$5:$Q$634,MATCH($A33,Payments!$A$5:$A$634,0)) -> 7
A34: P0513 | B34: =INDEX(Payments!$C$5:$C$634,MATCH($A34,Payments!$A$5:$A$634,0)) -> V031 | C34: =INDEX(Payments!$B$5:$B$634,MATCH($A34,Payments!$A$5:$A$634,0)) -> 45958 | D34: =INDEX(Payments!$E$5:$E$634,MATCH($A34,Payments!$A$5:$A$634,0)) -> 4949.31 | E34: =INDEX(Payments!$Q$5:$Q$634,MATCH($A34,Payments!$A$5:$A$634,0)) -> 7
A35: P0600 | B35: =INDEX(Payments!$C$5:$C$634,MATCH($A35,Payments!$A$5:$A$634,0)) -> V031 | C35: =INDEX(Payments!$B$5:$B$634,MATCH($A35,Payments!$A$5:$A$634,0)) -> 46007 | D35: =INDEX(Payments!$E$5:$E$634,MATCH($A35,Payments!$A$5:$A$634,0)) -> 4974.35 | E35: =INDEX(Payments!$Q$5:$Q$634,MATCH($A35,Payments!$A$5:$A$634,0)) -> 7
A36: P0601 | B36: =INDEX(Payments!$C$5:$C$634,MATCH($A36,Payments!$A$5:$A$634,0)) -> V031 | C36: =INDEX(Payments!$B$5:$B$634,MATCH($A36,Payments!$A$5:$A$634,0)) -> 46007 | D36: =INDEX(Payments!$E$5:$E$634,MATCH($A36,Payments!$A$5:$A$634,0)) -> 4771.66 | E36: =INDEX(Payments!$Q$5:$Q$634,MATCH($A36,Payments!$A$5:$A$634,0)) -> 7
A37: P0012 | B37: =INDEX(Payments!$C$5:$C$634,MATCH($A37,Payments!$A$5:$A$634,0)) -> V012 | C37: =INDEX(Payments!$B$5:$B$634,MATCH($A37,Payments!$A$5:$A$634,0)) -> 45664 | D37: =INDEX(Payments!$E$5:$E$634,MATCH($A37,Payments!$A$5:$A$634,0)) -> 6340.75 | E37: =INDEX(Payments!$Q$5:$Q$634,MATCH($A37,Payments!$A$5:$A$634,0)) -> 5
A38: P0066 | B38: =INDEX(Payments!$C$5:$C$634,MATCH($A38,Payments!$A$5:$A$634,0)) -> V001 | C38: =INDEX(Payments!$B$5:$B$634,MATCH($A38,Payments!$A$5:$A$634,0)) -> 45694 | D38: =INDEX(Payments!$E$5:$E$634,MATCH($A38,Payments!$A$5:$A$634,0)) -> 85000 | E38: =INDEX(Payments!$Q$5:$Q$634,MATCH($A38,Payments!$A$5:$A$634,0)) -> 5
... A75: P0602 | B75: =INDEX(Payments!$C$5:$C$634,MATCH($A75,Payments!$A$5:$A$634,0)) -> V002 | C75: =INDEX(Payments!$B$5:$B$634,MATCH($A75,Payments!$A$5:$A$634,0)) -> 46008 | D75: =INDEX(Payments!$E$5:$E$634,MATCH($A75,Payments!$A$5:$A$634,0)) -> 4900 | E75: =INDEX(Payments!$Q$5:$Q$634,MATCH($A75,Payments!$A$5:$A$634,0)) -> 5
A78: High risk journal entries (ranked by engine, details are formulas)
A79: JE no | B79: User | C79: Posting date | D79: Total debit (USD) | E79: Score | F79: Reviewer disposition (input)
A80: 1796 | B80: =INDEX(JE_Entries!$H$5:$H$795,MATCH($A80,JE_Entries!$A$5:$A$795,0)) -> FIN03 | C80: =INDEX(JE_Entries!$F$5:$F$795,MATCH($A80,JE_Entries!$A$5:$A$795,0)) -> 46021 | D80: =INDEX(JE_Entries!$C$5:$C$795,MATCH($A80,JE_Entries!$A$5:$A$795,0)) -> 320000 | E80: =INDEX(JE_Entries!$Y$5:$Y$795,MATCH($A80,JE_Entries!$A$5:$A$795,0)) -> 8
A81: 1802 | B81: =INDEX(JE_Entries!$H$5:$H$795,MATCH($A81,JE_Entries!$A$5:$A$795,0)) -> FIN03 | C81: =INDEX(JE_Entries!$F$5:$F$795,MATCH($A81,JE_Entries!$A$5:$A$795,0)) -> 46022 | D81: =INDEX(JE_Entries!$C$5:$C$795,MATCH($A81,JE_Entries!$A$5:$A$795,0)) -> 410000 | E81: =INDEX(JE_Entries!$Y$5:$Y$795,MATCH($A81,JE_Entries!$A$5:$A$795,0)) -> 8
A82: 1791 | B82: =INDEX(JE_Entries!$H$5:$H$795,MATCH($A82,JE_Entries!$A$5:$A$795,0)) -> FIN03 | C82: =INDEX(JE_Entries!$F$5:$F$795,MATCH($A82,JE_Entries!$A$5:$A$795,0)) -> 46020 | D82: =INDEX(JE_Entries!$C$5:$C$795,MATCH($A82,JE_Entries!$A$5:$A$795,0)) -> 250000 | E82: =INDEX(JE_Entries!$Y$5:$Y$795,MATCH($A82,JE_Entries!$A$5:$A$795,0)) -> 6
A83: 1793 | B83: =INDEX(JE_Entries!$H$5:$H$795,MATCH($A83,JE_Entries!$A$5:$A$795,0)) -> FIN01 | C83: =INDEX(JE_Entries!$F$5:$F$795,MATCH($A83,JE_Entries!$A$5:$A$795,0)) -> 46021 | D83: =INDEX(JE_Entries!$C$5:$C$795,MATCH($A83,JE_Entries!$A$5:$A$795,0)) -> 17623.64 | E83: =INDEX(JE_Entries!$Y$5:$Y$795,MATCH($A83,JE_Entries!$A$5:$A$795,0)) -> 6
A84: 1795 | B84: =INDEX(JE_Entries!$H$5:$H$795,MATCH($A84,JE_Entries!$A$5:$A$795,0)) -> FIN03 | C84: =INDEX(JE_Entries!$F$5:$F$795,MATCH($A84,JE_Entries!$A$5:$A$795,0)) -> 46021 | D84: =INDEX(JE_Entries!$C$5:$C$795,MATCH($A84,JE_Entries!$A$5:$A$795,0)) -> 180000 | E84: =INDEX(JE_Entries!$Y$5:$Y$795,MATCH($A84,JE_Entries!$A$5:$A$795,0)) -> 6
A85: 1800 | B85: =INDEX(JE_Entries!$H$5:$H$795,MATCH($A85,JE_Entries!$A$5:$A$795,0)) -> FIN03 | C85: =INDEX(JE_Entries!$F$5:$F$795,MATCH($A85,JE_Entries!$A$5:$A$795,0)) -> 46022 | D85: =INDEX(JE_Entries!$C$5:$C$795,MATCH($A85,JE_Entries!$A$5:$A$795,0)) -> 150000 | E85: =INDEX(JE_Entries!$Y$5:$Y$795,MATCH($A85,JE_Entries!$A$5:$A$795,0)) -> 6
A86: 1124 | B86: =INDEX(JE_Entries!$H$5:$H$795,MATCH($A86,JE_Entries!$A$5:$A$795,0)) -> FIN05 | C86: =INDEX(JE_Entries!$F$5:$F$795,MATCH($A86,JE_Entries!$A$5:$A$795,0)) -> 45707 | D86: =INDEX(JE_Entries!$C$5:$C$795,MATCH($A86,JE_Entries!$A$5:$A$795,0)) -> 765.54 | E86: =INDEX(JE_Entries!$Y$5:$Y$795,MATCH($A86,JE_Entries!$A$5:$A$795,0)) -> 5
A87: 1464 | B87: =INDEX(JE_Entries!$H$5:$H$795,MATCH($A87,JE_Entries!$A$5:$A$795,0)) -> FIN05 | C87: =INDEX(JE_Entries!$F$5:$F$795,MATCH($A87,JE_Entries!$A$5:$A$795,0)) -> 45859 | D87: =INDEX(JE_Entries!$C$5:$C$795,MATCH($A87,JE_Entries!$A$5:$A$795,0)) -> 33161.32 | E87: =INDEX(JE_Entries!$Y$5:$Y$795,MATCH($A87,JE_Entries!$A$5:$A$795,0)) -> 5

Sheet Checks
A1: Controls
A2: Sample / demonstration data only. No real company, vendor, employee or transaction.
A3: Differences must be zero. Overall result must read PASS.
A4: Control | B4: Result | C4: Expected | D4: Pass?
A5: Payments listed less Benford digit counts | B5: =COUNTA(Payments!$A$5:$A$634)-Benford!B15 -> 0 | C5: 0 | D5: =IF(ABS(B5-C5)<0.005,"OK","FAIL") -> OK
A6: Payments listed less Vendor_Benford counts | B6: =COUNTA(Payments!$A$5:$A$634)-SUM(Vendor_Benford!$B$6:$B$50) -> 0 | C6: 0 | D6: =IF(ABS(B6-C6)<0.005,"OK","FAIL") -> OK
A7: JE lines in JE_Lines less lines assigned to entries | B7: =COUNTA(JE_Lines!$A$5:$A$1733)-SUM(JE_Entries!$B$5:$B$795) -> 0 | C7: 0 | D7: =IF(ABS(B7-C7)<0.005,"OK","FAIL") -> OK
A8: Total debits less total credits per JE_Lines, less sum of entry differences | B8: =SUM(JE_Lines!$G$5:$G$1733)-SUM(JE_Lines!$H$5:$H$1733)-SUM(JE_Entries!$E$5:$E$795) -> 0 | C8: 0 | D8: =IF(ABS(B8-C8)<0.005,"OK","FAIL") -> OK
A9: Every JE line has a class (count of errors) | B9: =SUMPRODUCT(--ISERROR(JE_Lines!$F$5:$F$1733)) -> 0 | C9: 0 | D9: =IF(ABS(B9-C9)<0.005,"OK","FAIL") -> OK
A10: Errors in Payments flag and score columns | B10: =SUMPRODUCT(--ISERROR(Payments!$G$5:$R$634)) -> 0 | C10: 0 | D10: =IF(ABS(B10-C10)<0.005,"OK","FAIL") -> OK
A11: Errors in JE_Entries flag and score columns | B11: =SUMPRODUCT(--ISERROR(JE_Entries!$B$5:$Z$795)) -> 0 | C11: 0 | D11: =IF(ABS(B11-C11)<0.005,"OK","FAIL") -> OK
A12: High risk payments in list less High in Payments | B12: =COUNTA(Exceptions!$A$27:$A$75)-COUNTIF(Payments!$R$5:$R$634,"High") -> 0 | C12: 0 | D12: =IF(ABS(B12-C12)<0.005,"OK","FAIL") -> OK
A13: High risk entries in list less High in JE_Entries | B13: =COUNTA(Exceptions!$A$80:$A$87)-COUNTIF(JE_Entries!$Z$5:$Z$795,"High") -> 0 | C13: 0 | D13: =IF(ABS(B13-C13)<0.005,"OK","FAIL") -> OK
A14: Duplicate payment IDs | B14: =SUMPRODUCT(--(COUNTIF(Payments!$A$5:$A$634,Payments!$A$5:$A$634)>1)) -> 0 | C14: 0 | D14: =IF(ABS(B14-C14)<0.005,"OK","FAIL") -> OK
A15: Duplicate JE numbers in JE_Entries | B15: =SUMPRODUCT(--(COUNTIF(JE_Entries!$A$5:$A$795,JE_Entries!$A$5:$A$795)>1)) -> 0 | C15: 0 | D15: =IF(ABS(B15-C15)<0.005,"OK","FAIL") -> OK
A16: Answer key rows with lookup errors | B16: =SUMPRODUCT(--ISERROR(Answer_Key!$F$5:$F$261)) -> 0 | C16: 0 | D16: =IF(ABS(B16-C16)<0.005,"OK","FAIL") -> OK
A18: OVERALL | D18: =IF(COUNTIF(D5:D16,"FAIL")=0,"PASS","FAIL") -> PASS
